{"results": [{"filename": "318.jpg", "rects": []}, {"filename": "325.jpg", "rects": [{"xmin": 0, "xmax": 2429, "ymin": 1508, "ymax": 1550, "confidence": 0.9999910593032837, "label": "defect7"}]}, {"filename": "470.jpg", "rects": [{"xmin": 6, "xmax": 2560, "ymin": 687, "ymax": 990, "confidence": 0.9992635846138, "label": "defect8"}]}, {"filename": "233.jpg", "rects": [{"xmin": 22, "xmax": 2558, "ymin": 497, "ymax": 755, "confidence": 0.9990307092666626, "label": "defect2"}]}, {"filename": "367.jpg", "rects": [{"xmin": 21, "xmax": 2560, "ymin": 740, "ymax": 806, "confidence": 0.9993448853492737, "label": "defect7"}]}, {"filename": "347.jpg", "rects": [{"xmin": 0, "xmax": 2560, "ymin": 406, "ymax": 491, "confidence": 0.9932517409324646, "label": "defect3"}]}, {"filename": "162.jpg", "rects": [{"xmin": 1253, "xmax": 1619, "ymin": 1056, "ymax": 1199, "confidence": 0.9794893264770508, "label": "defect5"}]}, {"filename": "125.jpg", "rects": [{"xmin": 27, "xmax": 2560, "ymin": 526, "ymax": 745, "confidence": 0.9819038510322571, "label": "defect3"}, {"xmin": 2, "xmax": 2560, "ymin": 32, "ymax": 439, "confidence": 0.8565912246704102, "label": "defect3"}, {"xmin": 763, "xmax": 1431, "ymin": 18, "ymax": 69, "confidence": 0.612982451915741, "label": "defect1"}]}, {"filename": "97.jpg", "rects": [{"xmin": 0, "xmax": 2544, "ymin": 1049, "ymax": 1181, "confidence": 0.9999765157699585, "label": "defect4"}]}, {"filename": "213.jpg", "rects": [{"xmin": 88, "xmax": 2524, "ymin": 1752, "ymax": 1836, "confidence": 0.8386440277099609, "label": "defect7"}]}, {"filename": "482.jpg", "rects": [{"xmin": 56, "xmax": 2560, "ymin": 1466, "ymax": 1562, "confidence": 0.999715268611908, "label": "defect4"}]}, {"filename": "32.jpg", "rects": [{"xmin": 0, "xmax": 2541, "ymin": 900, "ymax": 1220, "confidence": 0.9996659755706787, "label": "defect8"}]}, {"filename": "65.jpg", "rects": [{"xmin": 21, "xmax": 2560, "ymin": 778, "ymax": 849, "confidence": 0.9999783039093018, "label": "defect7"}]}, {"filename": "422.jpg", "rects": [{"xmin": 0, "xmax": 2560, "ymin": 707, "ymax": 1344, "confidence": 0.9986666440963745, "label": "defect8"}]}, {"filename": "331.jpg", "rects": [{"xmin": 0, "xmax": 2522, "ymin": 1071, "ymax": 1457, "confidence": 0.9999854564666748, "label": "defect0"}]}, {"filename": "417.jpg", "rects": [{"xmin": 1, "xmax": 2540, "ymin": 617, "ymax": 1157, "confidence": 0.9972397089004517, "label": "defect8"}]}, {"filename": "313.jpg", "rects": [{"xmin": 0, "xmax": 2560, "ymin": 728, "ymax": 880, "confidence": 0.9999743700027466, "label": "defect2"}, {"xmin": 1254, "xmax": 1394, "ymin": 872, "ymax": 954, "confidence": 0.6302692890167236, "label": "defect9"}, {"xmin": 1246, "xmax": 1309, "ymin": 720, "ymax": 756, "confidence": 0.36090537905693054, "label": "defect9"}, {"xmin": 1474, "xmax": 1536, "ymin": 1094, "ymax": 1148, "confidence": 0.3474794924259186, "label": "defect9"}, {"xmin": 55, "xmax": 559, "ymin": 964, "ymax": 1179, "confidence": 0.30964621901512146, "label": "defect9"}]}, {"filename": "39.jpg", "rects": [{"xmin": 0, "xmax": 2560, "ymin": 149, "ymax": 638, "confidence": 0.9964845180511475, "label": "defect0"}]}, {"filename": "66.jpg", "rects": [{"xmin": 0, "xmax": 2560, "ymin": 1184, "ymax": 1347, "confidence": 0.9999858140945435, "label": "defect4"}]}, {"filename": "408.jpg", "rects": []}, {"filename": "159.jpg", "rects": [{"xmin": 1365, "xmax": 1843, "ymin": 1271, "ymax": 1432, "confidence": 0.9979627132415771, "label": "defect5"}, {"xmin": 766, "xmax": 2560, "ymin": 1301, "ymax": 1398, "confidence": 0.32071995735168457, "label": "defect1"}]}, {"filename": "416.jpg", "rects": []}, {"filename": "296.jpg", "rects": [{"xmin": 1307, "xmax": 1420, "ymin": 1015, "ymax": 1138, "confidence": 0.9998849630355835, "label": "defect9"}, {"xmin": 408, "xmax": 480, "ymin": 1462, "ymax": 1553, "confidence": 0.403079628944397, "label": "defect9"}, {"xmin": 1330, "xmax": 1397, "ymin": 1016, "ymax": 1125, "confidence": 0.6263598203659058, "label": "defect1"}]}, {"filename": "189.jpg", "rects": []}, {"filename": "130.jpg", "rects": [{"xmin": 358, "xmax": 2560, "ymin": 1615, "ymax": 1730, "confidence": 0.9888781905174255, "label": "defect4"}, {"xmin": 2308, "xmax": 2365, "ymin": 1798, "ymax": 1845, "confidence": 0.36534157395362854, "label": "defect9"}]}, {"filename": "294.jpg", "rects": [{"xmin": 0, "xmax": 2554, "ymin": 643, "ymax": 1020, "confidence": 0.9999816417694092, "label": "defect0"}]}, {"filename": "14.jpg", "rects": []}, {"filename": "333.jpg", "rects": [{"xmin": 0, "xmax": 2505, "ymin": 986, "ymax": 1090, "confidence": 0.9998726844787598, "label": "defect2"}, {"xmin": 2406, "xmax": 2560, "ymin": 1106, "ymax": 1231, "confidence": 0.34790340065956116, "label": "defect9"}, {"xmin": 2268, "xmax": 2378, "ymin": 1278, "ymax": 1393, "confidence": 0.318657249212265, "label": "defect9"}]}, {"filename": "316.jpg", "rects": []}, {"filename": "299.jpg", "rects": [{"xmin": 1, "xmax": 2560, "ymin": 609, "ymax": 740, "confidence": 0.99986732006073, "label": "defect2"}, {"xmin": 2399, "xmax": 2479, "ymin": 858, "ymax": 915, "confidence": 0.46544864773750305, "label": "defect9"}]}, {"filename": "197.jpg", "rects": [{"xmin": 1406, "xmax": 1482, "ymin": 557, "ymax": 601, "confidence": 0.8854249715805054, "label": "defect9"}, {"xmin": 316, "xmax": 871, "ymin": 566, "ymax": 794, "confidence": 0.34325867891311646, "label": "defect9"}]}, {"filename": "68.jpg", "rects": [{"xmin": 31, "xmax": 2556, "ymin": 854, "ymax": 982, "confidence": 0.9993077516555786, "label": "defect2"}, {"xmin": 2433, "xmax": 2548, "ymin": 1088, "ymax": 1258, "confidence": 0.4189857244491577, "label": "defect9"}]}, {"filename": "110.jpg", "rects": [{"xmin": 43, "xmax": 2555, "ymin": 833, "ymax": 978, "confidence": 0.9921888113021851, "label": "defect2"}, {"xmin": 1392, "xmax": 1486, "ymin": 982, "ymax": 1045, "confidence": 0.5180535912513733, "label": "defect9"}]}, {"filename": "382.jpg", "rects": []}, {"filename": "158.jpg", "rects": [{"xmin": 31, "xmax": 2560, "ymin": 1296, "ymax": 1559, "confidence": 0.9998829364776611, "label": "defect4"}, {"xmin": 486, "xmax": 589, "ymin": 1127, "ymax": 1210, "confidence": 0.3112209737300873, "label": "defect9"}]}, {"filename": "179.jpg", "rects": []}, {"filename": "135.jpg", "rects": [{"xmin": 1438, "xmax": 1522, "ymin": 598, "ymax": 648, "confidence": 0.7288215756416321, "label": "defect9"}, {"xmin": 622, "xmax": 2560, "ymin": 747, "ymax": 831, "confidence": 0.37302476167678833, "label": "defect1"}]}, {"filename": "321.jpg", "rects": [{"xmin": 2, "xmax": 2560, "ymin": 1403, "ymax": 1562, "confidence": 0.9998425245285034, "label": "defect2"}, {"xmin": 851, "xmax": 919, "ymin": 1664, "ymax": 1770, "confidence": 0.5153141617774963, "label": "defect9"}]}, {"filename": "434.jpg", "rects": [{"xmin": 0, "xmax": 2560, "ymin": 457, "ymax": 833, "confidence": 0.9999634027481079, "label": "defect0"}]}, {"filename": "262.jpg", "rects": [{"xmin": 60, "xmax": 2560, "ymin": 1664, "ymax": 1708, "confidence": 0.9999947547912598, "label": "defect7"}]}, {"filename": "53.jpg", "rects": [{"xmin": 0, "xmax": 2560, "ymin": 1198, "ymax": 1291, "confidence": 0.9998763799667358, "label": "defect4"}]}, {"filename": "202.jpg", "rects": [{"xmin": 2, "xmax": 2560, "ymin": 1306, "ymax": 1613, "confidence": 0.9996815919876099, "label": "defect8"}, {"xmin": 667, "xmax": 2087, "ymin": 990, "ymax": 1099, "confidence": 0.3037487864494324, "label": "defect1"}]}, {"filename": "181.jpg", "rects": [{"xmin": 0, "xmax": 2560, "ymin": 1072, "ymax": 1728, "confidence": 0.9992750287055969, "label": "defect8"}]}, {"filename": "452.jpg", "rects": [{"xmin": 0, "xmax": 2557, "ymin": 774, "ymax": 1348, "confidence": 0.9994865655899048, "label": "defect8"}]}, {"filename": "372.jpg", "rects": [{"xmin": 2, "xmax": 2560, "ymin": 1045, "ymax": 1197, "confidence": 0.9996401071548462, "label": "defect4"}]}, {"filename": "370.jpg", "rects": [{"xmin": 118, "xmax": 2528, "ymin": 848, "ymax": 1214, "confidence": 0.9974929094314575, "label": "defect0"}, {"xmin": 2514, "xmax": 2557, "ymin": 1120, "ymax": 1166, "confidence": 0.635779082775116, "label": "defect9"}]}, {"filename": "12.jpg", "rects": [{"xmin": 0, "xmax": 2378, "ymin": 993, "ymax": 1104, "confidence": 0.985489547252655, "label": "defect4"}]}, {"filename": "468.jpg", "rects": [{"xmin": 1812, "xmax": 1947, "ymin": 877, "ymax": 937, "confidence": 0.9930007457733154, "label": "defect9"}, {"xmin": 145, "xmax": 2492, "ymin": 844, "ymax": 1348, "confidence": 0.8621533513069153, "label": "defect1"}]}, {"filename": "217.jpg", "rects": [{"xmin": 33, "xmax": 2551, "ymin": 1154, "ymax": 1349, "confidence": 0.9997448325157166, "label": "defect4"}]}, {"filename": "198.jpg", "rects": [{"xmin": 23, "xmax": 2560, "ymin": 1224, "ymax": 1591, "confidence": 0.9940756559371948, "label": "defect8"}]}, {"filename": "122.jpg", "rects": [{"xmin": 81, "xmax": 2560, "ymin": 717, "ymax": 763, "confidence": 0.8944736123085022, "label": "defect7"}]}, {"filename": "438.jpg", "rects": [{"xmin": 0, "xmax": 2542, "ymin": 529, "ymax": 894, "confidence": 0.9896416068077087, "label": "defect8"}]}, {"filename": "113.jpg", "rects": [{"xmin": 456, "xmax": 2560, "ymin": 1460, "ymax": 1557, "confidence": 0.9588651657104492, "label": "defect4"}]}, {"filename": "187.jpg", "rects": [{"xmin": 743, "xmax": 794, "ymin": 1444, "ymax": 1511, "confidence": 0.9999793767929077, "label": "defect9"}, {"xmin": 1161, "xmax": 1234, "ymin": 623, "ymax": 673, "confidence": 0.8078694939613342, "label": "defect9"}, {"xmin": 190, "xmax": 235, "ymin": 717, "ymax": 760, "confidence": 0.41040927171707153, "label": "defect9"}]}, {"filename": "393.jpg", "rects": [{"xmin": 635, "xmax": 723, "ymin": 773, "ymax": 915, "confidence": 0.5739395618438721, "label": "defect9"}, {"xmin": 837, "xmax": 922, "ymin": 796, "ymax": 867, "confidence": 0.3111015856266022, "label": "defect9"}]}, {"filename": "96.jpg", "rects": [{"xmin": 38, "xmax": 2560, "ymin": 920, "ymax": 1006, "confidence": 0.99994957447052, "label": "defect7"}]}, {"filename": "463.jpg", "rects": [{"xmin": 0, "xmax": 2547, "ymin": 795, "ymax": 1372, "confidence": 0.9997878670692444, "label": "defect8"}]}, {"filename": "324.jpg", "rects": [{"xmin": 2, "xmax": 2550, "ymin": 447, "ymax": 1146, "confidence": 0.8852184414863586, "label": "defect3"}]}, {"filename": "473.jpg", "rects": [{"xmin": 1671, "xmax": 1715, "ymin": 1047, "ymax": 1097, "confidence": 0.874436616897583, "label": "defect9"}]}, {"filename": "214.jpg", "rects": [{"xmin": 2, "xmax": 2560, "ymin": 1018, "ymax": 1338, "confidence": 0.9990255832672119, "label": "defect8"}]}, {"filename": "427.jpg", "rects": [{"xmin": 9, "xmax": 2560, "ymin": 799, "ymax": 925, "confidence": 0.9875468611717224, "label": "defect2"}]}, {"filename": "271.jpg", "rects": []}, {"filename": "238.jpg", "rects": [{"xmin": 6, "xmax": 2553, "ymin": 1033, "ymax": 1184, "confidence": 0.9999343156814575, "label": "defect4"}]}, {"filename": "131.jpg", "rects": [{"xmin": 0, "xmax": 2466, "ymin": 193, "ymax": 264, "confidence": 0.9942651391029358, "label": "defect3"}]}, {"filename": "355.jpg", "rects": []}, {"filename": "146.jpg", "rects": []}, {"filename": "200.jpg", "rects": [{"xmin": 1369, "xmax": 1435, "ymin": 653, "ymax": 711, "confidence": 0.9999740123748779, "label": "defect9"}, {"xmin": 1898, "xmax": 1953, "ymin": 393, "ymax": 438, "confidence": 0.5082598328590393, "label": "defect9"}]}, {"filename": "315.jpg", "rects": []}, {"filename": "63.jpg", "rects": [{"xmin": 1, "xmax": 2560, "ymin": 792, "ymax": 1109, "confidence": 0.9995517134666443, "label": "defect8"}]}, {"filename": "42.jpg", "rects": []}, {"filename": "363.jpg", "rects": [{"xmin": 23, "xmax": 2560, "ymin": 1065, "ymax": 1113, "confidence": 0.9823348522186279, "label": "defect7"}]}, {"filename": "388.jpg", "rects": [{"xmin": 87, "xmax": 2560, "ymin": 1141, "ymax": 1241, "confidence": 0.9995560050010681, "label": "defect7"}]}, {"filename": "442.jpg", "rects": [{"xmin": 1353, "xmax": 1812, "ymin": 1100, "ymax": 1532, "confidence": 0.9578067064285278, "label": "defect0"}, {"xmin": 930, "xmax": 993, "ymin": 1103, "ymax": 1155, "confidence": 0.9486346244812012, "label": "defect9"}]}, {"filename": "444.jpg", "rects": [{"xmin": 27, "xmax": 2560, "ymin": 1396, "ymax": 1504, "confidence": 0.9999550580978394, "label": "defect4"}]}, {"filename": "25.jpg", "rects": []}, {"filename": "279.jpg", "rects": []}, {"filename": "454.jpg", "rects": [{"xmin": 580, "xmax": 2560, "ymin": 1079, "ymax": 1168, "confidence": 0.7525581121444702, "label": "defect0"}, {"xmin": 27, "xmax": 2545, "ymin": 1310, "ymax": 1565, "confidence": 0.7524267435073853, "label": "defect4"}, {"xmin": 39, "xmax": 2552, "ymin": 1054, "ymax": 1178, "confidence": 0.6339446902275085, "label": "defect7"}]}, {"filename": "38.jpg", "rects": [{"xmin": 0, "xmax": 2549, "ymin": 736, "ymax": 862, "confidence": 0.9999808073043823, "label": "defect2"}, {"xmin": 956, "xmax": 1041, "ymin": 977, "ymax": 1033, "confidence": 0.4118032157421112, "label": "defect9"}]}, {"filename": "275.jpg", "rects": [{"xmin": 0, "xmax": 2548, "ymin": 866, "ymax": 1212, "confidence": 0.9998806715011597, "label": "defect0"}]}, {"filename": "342.jpg", "rects": [{"xmin": 843, "xmax": 902, "ymin": 1125, "ymax": 1169, "confidence": 0.998468816280365, "label": "defect9"}, {"xmin": 1293, "xmax": 1340, "ymin": 934, "ymax": 985, "confidence": 0.5828390121459961, "label": "defect9"}, {"xmin": 231, "xmax": 419, "ymin": 1027, "ymax": 1217, "confidence": 0.500084400177002, "label": "defect9"}, {"xmin": 2106, "xmax": 2176, "ymin": 1084, "ymax": 1185, "confidence": 0.426738977432251, "label": "defect9"}]}, {"filename": "40.jpg", "rects": [{"xmin": 66, "xmax": 2518, "ymin": 482, "ymax": 538, "confidence": 0.9807987809181213, "label": "defect7"}]}, {"filename": "112.jpg", "rects": [{"xmin": 3, "xmax": 2516, "ymin": 735, "ymax": 1080, "confidence": 0.9995383024215698, "label": "defect8"}]}, {"filename": "292.jpg", "rects": [{"xmin": 1228, "xmax": 1296, "ymin": 807, "ymax": 855, "confidence": 0.999984860420227, "label": "defect9"}, {"xmin": 0, "xmax": 2530, "ymin": 549, "ymax": 666, "confidence": 0.9971452355384827, "label": "defect2"}]}, {"filename": "184.jpg", "rects": [{"xmin": 0, "xmax": 2438, "ymin": 1565, "ymax": 1625, "confidence": 0.9999386072158813, "label": "defect7"}]}, {"filename": "344.jpg", "rects": [{"xmin": 5, "xmax": 2560, "ymin": 665, "ymax": 1079, "confidence": 0.9997718930244446, "label": "defect0"}]}, {"filename": "357.jpg", "rects": [{"xmin": 33, "xmax": 2560, "ymin": 825, "ymax": 1173, "confidence": 0.9999709129333496, "label": "defect0"}]}, {"filename": "30.jpg", "rects": []}, {"filename": "121.jpg", "rects": [{"xmin": 240, "xmax": 2553, "ymin": 822, "ymax": 920, "confidence": 0.9728221893310547, "label": "defect2"}, {"xmin": 1319, "xmax": 1512, "ymin": 947, "ymax": 1032, "confidence": 0.9425736665725708, "label": "defect9"}, {"xmin": 1968, "xmax": 2140, "ymin": 960, "ymax": 1034, "confidence": 0.34411492943763733, "label": "defect9"}]}, {"filename": "471.jpg", "rects": [{"xmin": 40, "xmax": 2560, "ymin": 1117, "ymax": 1349, "confidence": 0.9993190765380859, "label": "defect4"}]}, {"filename": "219.jpg", "rects": [{"xmin": 91, "xmax": 2097, "ymin": 1178, "ymax": 1444, "confidence": 0.980890154838562, "label": "defect5"}, {"xmin": 1638, "xmax": 1715, "ymin": 1000, "ymax": 1047, "confidence": 0.3238057792186737, "label": "defect9"}]}, {"filename": "47.jpg", "rects": [{"xmin": 0, "xmax": 2533, "ymin": 1167, "ymax": 1259, "confidence": 0.9929024577140808, "label": "defect4"}]}, {"filename": "232.jpg", "rects": [{"xmin": 0, "xmax": 2326, "ymin": 1159, "ymax": 1264, "confidence": 0.9951525926589966, "label": "defect4"}]}, {"filename": "280.jpg", "rects": [{"xmin": 1185, "xmax": 1296, "ymin": 968, "ymax": 1051, "confidence": 0.9996339082717896, "label": "defect9"}, {"xmin": 81, "xmax": 2560, "ymin": 792, "ymax": 919, "confidence": 0.9927782416343689, "label": "defect2"}]}, {"filename": "22.jpg", "rects": [{"xmin": 0, "xmax": 2556, "ymin": 812, "ymax": 1382, "confidence": 0.9996352195739746, "label": "defect8"}]}, {"filename": "258.jpg", "rects": [{"xmin": 0, "xmax": 2560, "ymin": 559, "ymax": 954, "confidence": 0.9999594688415527, "label": "defect0"}]}, {"filename": "36.jpg", "rects": [{"xmin": 24, "xmax": 2525, "ymin": 1512, "ymax": 1611, "confidence": 0.9479420185089111, "label": "defect6"}]}, {"filename": "24.jpg", "rects": [{"xmin": 169, "xmax": 2197, "ymin": 726, "ymax": 1143, "confidence": 0.4386084973812103, "label": "defect1"}]}, {"filename": "29.jpg", "rects": [{"xmin": 1613, "xmax": 1678, "ymin": 64, "ymax": 122, "confidence": 0.9958477020263672, "label": "defect9"}, {"xmin": 1506, "xmax": 1762, "ymin": 814, "ymax": 969, "confidence": 0.3228083550930023, "label": "defect9"}, {"xmin": 1907, "xmax": 1972, "ymin": 554, "ymax": 606, "confidence": 0.7931872606277466, "label": "defect9"}, {"xmin": 86, "xmax": 144, "ymin": 909, "ymax": 962, "confidence": 0.42172157764434814, "label": "defect9"}]}, {"filename": "402.jpg", "rects": [{"xmin": 0, "xmax": 2551, "ymin": 1350, "ymax": 1548, "confidence": 0.9999972581863403, "label": "defect2"}]}, {"filename": "89.jpg", "rects": [{"xmin": 7, "xmax": 2560, "ymin": 631, "ymax": 695, "confidence": 0.9967208504676819, "label": "defect7"}]}, {"filename": "364.jpg", "rects": []}, {"filename": "339.jpg", "rects": []}, {"filename": "423.jpg", "rects": [{"xmin": 0, "xmax": 2374, "ymin": 1617, "ymax": 1730, "confidence": 0.9957899451255798, "label": "defect4"}]}, {"filename": "138.jpg", "rects": []}, {"filename": "69.jpg", "rects": [{"xmin": 0, "xmax": 2560, "ymin": 712, "ymax": 1076, "confidence": 0.9999755620956421, "label": "defect0"}]}, {"filename": "3.jpg", "rects": [{"xmin": 0, "xmax": 2536, "ymin": 1101, "ymax": 1219, "confidence": 0.9997757077217102, "label": "defect4"}, {"xmin": 0, "xmax": 2219, "ymin": 1566, "ymax": 1638, "confidence": 0.6924706101417542, "label": "defect7"}, {"xmin": 1050, "xmax": 1117, "ymin": 730, "ymax": 827, "confidence": 0.3203679323196411, "label": "defect9"}, {"xmin": 1536, "xmax": 1786, "ymin": 748, "ymax": 869, "confidence": 0.31689056754112244, "label": "defect9"}]}, {"filename": "479.jpg", "rects": [{"xmin": 9, "xmax": 2560, "ymin": 481, "ymax": 564, "confidence": 0.8304360508918762, "label": "defect3"}, {"xmin": 0, "xmax": 2560, "ymin": 456, "ymax": 585, "confidence": 0.8518677949905396, "label": "defect4"}]}, {"filename": "142.jpg", "rects": [{"xmin": 0, "xmax": 2535, "ymin": 984, "ymax": 1083, "confidence": 0.9993289709091187, "label": "defect4"}]}, {"filename": "84.jpg", "rects": [{"xmin": 0, "xmax": 2168, "ymin": 1299, "ymax": 1408, "confidence": 0.9928978681564331, "label": "defect4"}, {"xmin": 2427, "xmax": 2503, "ymin": 1514, "ymax": 1564, "confidence": 0.8089768886566162, "label": "defect9"}, {"xmin": 1332, "xmax": 2144, "ymin": 1425, "ymax": 1615, "confidence": 0.3251330554485321, "label": "defect9"}]}, {"filename": "134.jpg", "rects": [{"xmin": 2068, "xmax": 2140, "ymin": 1152, "ymax": 1202, "confidence": 0.9993088245391846, "label": "defect9"}, {"xmin": 144, "xmax": 186, "ymin": 628, "ymax": 676, "confidence": 0.31478726863861084, "label": "defect9"}, {"xmin": 1194, "xmax": 1248, "ymin": 1070, "ymax": 1138, "confidence": 0.3827158212661743, "label": "defect9"}, {"xmin": 1772, "xmax": 1855, "ymin": 725, "ymax": 876, "confidence": 0.6703630685806274, "label": "defect1"}]}, {"filename": "445.jpg", "rects": [{"xmin": 29, "xmax": 2560, "ymin": 1562, "ymax": 1659, "confidence": 0.9999558925628662, "label": "defect4"}, {"xmin": 482, "xmax": 552, "ymin": 1697, "ymax": 1759, "confidence": 0.9680343270301819, "label": "defect9"}]}, {"filename": "139.jpg", "rects": []}, {"filename": "276.jpg", "rects": [{"xmin": 0, "xmax": 2547, "ymin": 1326, "ymax": 1445, "confidence": 0.9945573806762695, "label": "defect4"}]}, {"filename": "376.jpg", "rects": [{"xmin": 0, "xmax": 2520, "ymin": 424, "ymax": 732, "confidence": 0.9927167892456055, "label": "defect0"}]}, {"filename": "358.jpg", "rects": [{"xmin": 0, "xmax": 2560, "ymin": 982, "ymax": 1347, "confidence": 0.9993626475334167, "label": "defect0"}]}, {"filename": "88.jpg", "rects": [{"xmin": 0, "xmax": 2560, "ymin": 1092, "ymax": 1598, "confidence": 0.9973164200782776, "label": "defect8"}]}, {"filename": "210.jpg", "rects": [{"xmin": 22, "xmax": 2560, "ymin": 866, "ymax": 984, "confidence": 0.9999681711196899, "label": "defect2"}, {"xmin": 546, "xmax": 649, "ymin": 1138, "ymax": 1247, "confidence": 0.48550471663475037, "label": "defect9"}]}, {"filename": "106.jpg", "rects": []}, {"filename": "153.jpg", "rects": [{"xmin": 64, "xmax": 2560, "ymin": 385, "ymax": 434, "confidence": 0.9999721050262451, "label": "defect7"}]}, {"filename": "436.jpg", "rects": [{"xmin": 0, "xmax": 2544, "ymin": 984, "ymax": 1135, "confidence": 0.9940934777259827, "label": "defect4"}]}, {"filename": "458.jpg", "rects": [{"xmin": 29, "xmax": 2536, "ymin": 576, "ymax": 822, "confidence": 0.9990841150283813, "label": "defect2"}]}, {"filename": "457.jpg", "rects": [{"xmin": 26, "xmax": 2528, "ymin": 842, "ymax": 972, "confidence": 0.9980413913726807, "label": "defect2"}, {"xmin": 1126, "xmax": 1219, "ymin": 1183, "ymax": 1249, "confidence": 0.9808486700057983, "label": "defect9"}, {"xmin": 38, "xmax": 141, "ymin": 1194, "ymax": 1263, "confidence": 0.3465978801250458, "label": "defect9"}]}, {"filename": "221.jpg", "rects": [{"xmin": 334, "xmax": 398, "ymin": 1491, "ymax": 1541, "confidence": 0.7542968988418579, "label": "defect9"}]}, {"filename": "330.jpg", "rects": [{"xmin": 9, "xmax": 2555, "ymin": 693, "ymax": 1024, "confidence": 0.9986820816993713, "label": "defect8"}]}, {"filename": "474.jpg", "rects": []}, {"filename": "282.jpg", "rects": [{"xmin": 30, "xmax": 2560, "ymin": 1073, "ymax": 1586, "confidence": 0.9995642304420471, "label": "defect8"}]}, {"filename": "386.jpg", "rects": [{"xmin": 1901, "xmax": 1960, "ymin": 647, "ymax": 704, "confidence": 0.9712938070297241, "label": "defect9"}, {"xmin": 29, "xmax": 97, "ymin": 1058, "ymax": 1102, "confidence": 0.3082985281944275, "label": "defect9"}]}, {"filename": "467.jpg", "rects": []}, {"filename": "378.jpg", "rects": []}, {"filename": "493.jpg", "rects": [{"xmin": 8, "xmax": 2560, "ymin": 1106, "ymax": 1230, "confidence": 0.9988565444946289, "label": "defect4"}]}, {"filename": "103.jpg", "rects": [{"xmin": 14, "xmax": 2560, "ymin": 1378, "ymax": 1522, "confidence": 0.999997615814209, "label": "defect4"}, {"xmin": 1968, "xmax": 2029, "ymin": 1278, "ymax": 1332, "confidence": 0.3811838924884796, "label": "defect9"}]}, {"filename": "432.jpg", "rects": [{"xmin": 497, "xmax": 552, "ymin": 992, "ymax": 1045, "confidence": 0.9795499444007874, "label": "defect9"}, {"xmin": 1813, "xmax": 1866, "ymin": 613, "ymax": 663, "confidence": 0.7431100606918335, "label": "defect9"}, {"xmin": 1079, "xmax": 1128, "ymin": 585, "ymax": 631, "confidence": 0.42606255412101746, "label": "defect9"}, {"xmin": 1702, "xmax": 1767, "ymin": 1072, "ymax": 1134, "confidence": 0.41113966703414917, "label": "defect9"}, {"xmin": 34, "xmax": 116, "ymin": 1154, "ymax": 1262, "confidence": 0.3562527894973755, "label": "defect9"}, {"xmin": 566, "xmax": 634, "ymin": 1132, "ymax": 1258, "confidence": 0.59835284948349, "label": "defect1"}, {"xmin": 903, "xmax": 987, "ymin": 1027, "ymax": 1161, "confidence": 0.48553666472435, "label": "defect1"}, {"xmin": 20, "xmax": 94, "ymin": 1087, "ymax": 1239, "confidence": 0.4319206476211548, "label": "defect1"}]}, {"filename": "7.jpg", "rects": [{"xmin": 0, "xmax": 2529, "ymin": 724, "ymax": 796, "confidence": 0.9582695364952087, "label": "defect7"}]}, {"filename": "199.jpg", "rects": [{"xmin": 7, "xmax": 2556, "ymin": 565, "ymax": 1009, "confidence": 0.9999094009399414, "label": "defect0"}]}, {"filename": "484.jpg", "rects": []}, {"filename": "259.jpg", "rects": [{"xmin": 0, "xmax": 2560, "ymin": 165, "ymax": 239, "confidence": 0.9315207600593567, "label": "defect3"}]}, {"filename": "461.jpg", "rects": [{"xmin": 0, "xmax": 2552, "ymin": 1342, "ymax": 1587, "confidence": 0.7815857529640198, "label": "defect0"}]}, {"filename": "164.jpg", "rects": []}, {"filename": "117.jpg", "rects": [{"xmin": 11, "xmax": 2560, "ymin": 893, "ymax": 1013, "confidence": 0.9998878240585327, "label": "defect2"}, {"xmin": 2295, "xmax": 2508, "ymin": 1145, "ymax": 1287, "confidence": 0.4107424020767212, "label": "defect9"}, {"xmin": 112, "xmax": 201, "ymin": 1083, "ymax": 1139, "confidence": 0.304758220911026, "label": "defect9"}]}, {"filename": "43.jpg", "rects": [{"xmin": 63, "xmax": 2560, "ymin": 1118, "ymax": 1250, "confidence": 0.9778915643692017, "label": "defect4"}]}, {"filename": "186.jpg", "rects": [{"xmin": 375, "xmax": 2560, "ymin": 1147, "ymax": 1264, "confidence": 0.9876759052276611, "label": "defect4"}]}, {"filename": "216.jpg", "rects": []}, {"filename": "193.jpg", "rects": [{"xmin": 0, "xmax": 2540, "ymin": 1065, "ymax": 1129, "confidence": 0.9986961483955383, "label": "defect7"}]}, {"filename": "211.jpg", "rects": [{"xmin": 155, "xmax": 2516, "ymin": 981, "ymax": 1087, "confidence": 0.9976257681846619, "label": "defect2"}, {"xmin": 201, "xmax": 357, "ymin": 1125, "ymax": 1279, "confidence": 0.7112429738044739, "label": "defect9"}, {"xmin": 2007, "xmax": 2108, "ymin": 1132, "ymax": 1204, "confidence": 0.37926775217056274, "label": "defect9"}]}, {"filename": "170.jpg", "rects": [{"xmin": 33, "xmax": 2477, "ymin": 241, "ymax": 314, "confidence": 0.9520453810691833, "label": "defect3"}, {"xmin": 853, "xmax": 906, "ymin": 786, "ymax": 841, "confidence": 0.35691073536872864, "label": "defect9"}]}, {"filename": "415.jpg", "rects": [{"xmin": 1141, "xmax": 1214, "ymin": 470, "ymax": 526, "confidence": 0.9999219179153442, "label": "defect9"}, {"xmin": 1167, "xmax": 1326, "ymin": 788, "ymax": 885, "confidence": 0.5298278331756592, "label": "defect9"}]}, {"filename": "409.jpg", "rects": []}, {"filename": "399.jpg", "rects": [{"xmin": 0, "xmax": 2560, "ymin": 1008, "ymax": 1142, "confidence": 0.9997789263725281, "label": "defect4"}]}, {"filename": "225.jpg", "rects": [{"xmin": 0, "xmax": 2556, "ymin": 1333, "ymax": 1517, "confidence": 0.9999779462814331, "label": "defect2"}, {"xmin": 326, "xmax": 404, "ymin": 1709, "ymax": 1816, "confidence": 0.4727453887462616, "label": "defect9"}, {"xmin": 1228, "xmax": 1297, "ymin": 1685, "ymax": 1757, "confidence": 0.44363418221473694, "label": "defect9"}]}, {"filename": "234.jpg", "rects": []}, {"filename": "464.jpg", "rects": []}, {"filename": "167.jpg", "rects": [{"xmin": 16, "xmax": 2557, "ymin": 625, "ymax": 1005, "confidence": 0.9996559619903564, "label": "defect0"}]}, {"filename": "163.jpg", "rects": [{"xmin": 4, "xmax": 2560, "ymin": 916, "ymax": 1025, "confidence": 0.9999432563781738, "label": "defect2"}]}, {"filename": "469.jpg", "rects": []}, {"filename": "172.jpg", "rects": []}, {"filename": "246.jpg", "rects": []}, {"filename": "439.jpg", "rects": [{"xmin": 929, "xmax": 996, "ymin": 1083, "ymax": 1141, "confidence": 0.9999973773956299, "label": "defect9"}, {"xmin": 238, "xmax": 1820, "ymin": 1322, "ymax": 1414, "confidence": 0.9727358222007751, "label": "defect6"}]}, {"filename": "143.jpg", "rects": [{"xmin": 428, "xmax": 502, "ymin": 944, "ymax": 1057, "confidence": 0.8931626081466675, "label": "defect9"}, {"xmin": 2187, "xmax": 2258, "ymin": 609, "ymax": 660, "confidence": 0.42762210965156555, "label": "defect9"}]}, {"filename": "253.jpg", "rects": [{"xmin": 32, "xmax": 2560, "ymin": 696, "ymax": 947, "confidence": 0.9998012185096741, "label": "defect2"}]}, {"filename": "379.jpg", "rects": [{"xmin": 35, "xmax": 2560, "ymin": 515, "ymax": 662, "confidence": 0.981195330619812, "label": "defect2"}]}, {"filename": "322.jpg", "rects": []}, {"filename": "240.jpg", "rects": [{"xmin": 0, "xmax": 2549, "ymin": 753, "ymax": 1218, "confidence": 0.9989991784095764, "label": "defect0"}]}, {"filename": "356.jpg", "rects": []}, {"filename": "206.jpg", "rects": [{"xmin": 0, "xmax": 2546, "ymin": 892, "ymax": 1412, "confidence": 0.9993089437484741, "label": "defect8"}]}, {"filename": "343.jpg", "rects": []}, {"filename": "264.jpg", "rects": [{"xmin": 32, "xmax": 2560, "ymin": 864, "ymax": 987, "confidence": 0.9998003840446472, "label": "defect2"}]}, {"filename": "495.jpg", "rects": [{"xmin": 14, "xmax": 2560, "ymin": 942, "ymax": 1072, "confidence": 0.9928900003433228, "label": "defect4"}]}, {"filename": "102.jpg", "rects": [{"xmin": 0, "xmax": 2545, "ymin": 1404, "ymax": 1532, "confidence": 0.9998753070831299, "label": "defect4"}]}, {"filename": "128.jpg", "rects": [{"xmin": 0, "xmax": 2560, "ymin": 985, "ymax": 1099, "confidence": 0.9959973096847534, "label": "defect2"}]}, {"filename": "396.jpg", "rects": [{"xmin": 0, "xmax": 2553, "ymin": 893, "ymax": 1300, "confidence": 0.999228835105896, "label": "defect8"}]}, {"filename": "424.jpg", "rects": []}, {"filename": "472.jpg", "rects": [{"xmin": 0, "xmax": 2560, "ymin": 639, "ymax": 762, "confidence": 0.605984091758728, "label": "defect0"}, {"xmin": 368, "xmax": 2473, "ymin": 664, "ymax": 770, "confidence": 0.3542526364326477, "label": "defect1"}]}, {"filename": "119.jpg", "rects": [{"xmin": 9, "xmax": 2544, "ymin": 1072, "ymax": 1353, "confidence": 0.998544454574585, "label": "defect8"}]}, {"filename": "224.jpg", "rects": []}, {"filename": "401.jpg", "rects": [{"xmin": 0, "xmax": 2524, "ymin": 984, "ymax": 1088, "confidence": 0.9990870952606201, "label": "defect2"}, {"xmin": 501, "xmax": 684, "ymin": 1328, "ymax": 1397, "confidence": 0.9877533316612244, "label": "defect9"}]}, {"filename": "394.jpg", "rects": [{"xmin": 17, "xmax": 2547, "ymin": 151, "ymax": 226, "confidence": 0.9971972703933716, "label": "defect3"}, {"xmin": 1920, "xmax": 1988, "ymin": 717, "ymax": 785, "confidence": 0.596031129360199, "label": "defect9"}]}, {"filename": "230.jpg", "rects": [{"xmin": 0, "xmax": 2351, "ymin": 1287, "ymax": 1404, "confidence": 0.9958117008209229, "label": "defect4"}]}, {"filename": "410.jpg", "rects": [{"xmin": 0, "xmax": 2560, "ymin": 443, "ymax": 624, "confidence": 0.9981456995010376, "label": "defect3"}, {"xmin": 1199, "xmax": 1721, "ymin": 16, "ymax": 77, "confidence": 0.31190383434295654, "label": "defect1"}]}, {"filename": "175.jpg", "rects": [{"xmin": 19, "xmax": 2560, "ymin": 498, "ymax": 834, "confidence": 0.9996471405029297, "label": "defect8"}]}, {"filename": "150.jpg", "rects": []}, {"filename": "124.jpg", "rects": [{"xmin": 0, "xmax": 2560, "ymin": 921, "ymax": 1022, "confidence": 0.9999185800552368, "label": "defect2"}, {"xmin": 1321, "xmax": 1470, "ymin": 1266, "ymax": 1363, "confidence": 0.998757004737854, "label": "defect9"}, {"xmin": 1789, "xmax": 1980, "ymin": 1028, "ymax": 1150, "confidence": 0.7489833831787109, "label": "defect9"}, {"xmin": 32, "xmax": 318, "ymin": 1048, "ymax": 1155, "confidence": 0.37851887941360474, "label": "defect9"}, {"xmin": 1003, "xmax": 1083, "ymin": 1087, "ymax": 1140, "confidence": 0.3230974078178406, "label": "defect9"}, {"xmin": 1675, "xmax": 1840, "ymin": 1208, "ymax": 1335, "confidence": 0.3098018169403076, "label": "defect9"}]}, {"filename": "148.jpg", "rects": [{"xmin": 53, "xmax": 2520, "ymin": 1162, "ymax": 1692, "confidence": 0.9909018874168396, "label": "defect4"}]}, {"filename": "95.jpg", "rects": []}, {"filename": "156.jpg", "rects": [{"xmin": 1180, "xmax": 2560, "ymin": 991, "ymax": 1094, "confidence": 0.36425894498825073, "label": "defect1"}, {"xmin": 854, "xmax": 906, "ymin": 880, "ymax": 925, "confidence": 0.3171420991420746, "label": "defect9"}, {"xmin": 1229, "xmax": 1296, "ymin": 853, "ymax": 901, "confidence": 0.30074551701545715, "label": "defect9"}]}, {"filename": "239.jpg", "rects": [{"xmin": 0, "xmax": 2560, "ymin": 1703, "ymax": 1767, "confidence": 0.9950095415115356, "label": "defect7"}]}, {"filename": "114.jpg", "rects": [{"xmin": 730, "xmax": 780, "ymin": 940, "ymax": 1035, "confidence": 0.9696542620658875, "label": "defect1"}, {"xmin": 996, "xmax": 1076, "ymin": 1065, "ymax": 1197, "confidence": 0.4628412425518036, "label": "defect1"}, {"xmin": 2371, "xmax": 2437, "ymin": 1015, "ymax": 1122, "confidence": 0.6522623896598816, "label": "defect9"}, {"xmin": 2283, "xmax": 2350, "ymin": 938, "ymax": 990, "confidence": 0.5447539687156677, "label": "defect9"}, {"xmin": 2045, "xmax": 2112, "ymin": 1211, "ymax": 1268, "confidence": 0.5236048698425293, "label": "defect9"}, {"xmin": 207, "xmax": 356, "ymin": 439, "ymax": 541, "confidence": 0.3929615318775177, "label": "defect9"}, {"xmin": 1429, "xmax": 1927, "ymin": 1020, "ymax": 1331, "confidence": 0.386213093996048, "label": "defect9"}, {"xmin": 24, "xmax": 87, "ymin": 1142, "ymax": 1194, "confidence": 0.3044638931751251, "label": "defect9"}]}, {"filename": "481.jpg", "rects": [{"xmin": 0, "xmax": 2432, "ymin": 817, "ymax": 930, "confidence": 0.9938096404075623, "label": "defect2"}, {"xmin": 2325, "xmax": 2551, "ymin": 1039, "ymax": 1178, "confidence": 0.3076786994934082, "label": "defect9"}, {"xmin": 1036, "xmax": 1255, "ymin": 951, "ymax": 1042, "confidence": 0.3020358979701996, "label": "defect9"}]}, {"filename": "354.jpg", "rects": [{"xmin": 9, "xmax": 2552, "ymin": 945, "ymax": 1323, "confidence": 0.9992932081222534, "label": "defect0"}]}, {"filename": "196.jpg", "rects": [{"xmin": 26, "xmax": 2552, "ymin": 1043, "ymax": 1203, "confidence": 0.9999713897705078, "label": "defect4"}]}, {"filename": "223.jpg", "rects": [{"xmin": 0, "xmax": 2554, "ymin": 975, "ymax": 1335, "confidence": 0.9995629191398621, "label": "defect0"}]}, {"filename": "448.jpg", "rects": [{"xmin": 1887, "xmax": 2137, "ymin": 1340, "ymax": 1382, "confidence": 0.9698691964149475, "label": "defect0"}]}, {"filename": "278.jpg", "rects": [{"xmin": 0, "xmax": 2560, "ymin": 1666, "ymax": 1718, "confidence": 0.9552177786827087, "label": "defect7"}]}, {"filename": "77.jpg", "rects": [{"xmin": 1, "xmax": 2557, "ymin": 1223, "ymax": 1344, "confidence": 0.9999911785125732, "label": "defect4"}]}, {"filename": "420.jpg", "rects": [{"xmin": 2085, "xmax": 2159, "ymin": 966, "ymax": 1032, "confidence": 0.9999998807907104, "label": "defect9"}, {"xmin": 1730, "xmax": 1789, "ymin": 1133, "ymax": 1191, "confidence": 0.7642760276794434, "label": "defect9"}, {"xmin": 600, "xmax": 667, "ymin": 1457, "ymax": 1503, "confidence": 0.32141679525375366, "label": "defect9"}]}, {"filename": "466.jpg", "rects": []}, {"filename": "141.jpg", "rects": [{"xmin": 575, "xmax": 2016, "ymin": 1546, "ymax": 1636, "confidence": 0.8672654628753662, "label": "defect6"}]}, {"filename": "497.jpg", "rects": [{"xmin": 0, "xmax": 2560, "ymin": 881, "ymax": 1016, "confidence": 0.9999523162841797, "label": "defect2"}, {"xmin": 2039, "xmax": 2119, "ymin": 1196, "ymax": 1259, "confidence": 0.6014916896820068, "label": "defect9"}, {"xmin": 1364, "xmax": 1650, "ymin": 1029, "ymax": 1119, "confidence": 0.3432157337665558, "label": "defect9"}]}, {"filename": "16.jpg", "rects": []}, {"filename": "74.jpg", "rects": [{"xmin": 33, "xmax": 2560, "ymin": 921, "ymax": 1075, "confidence": 0.999005138874054, "label": "defect4"}]}, {"filename": "75.jpg", "rects": [{"xmin": 0, "xmax": 2419, "ymin": 1734, "ymax": 1790, "confidence": 0.9999490976333618, "label": "defect7"}]}, {"filename": "329.jpg", "rects": [{"xmin": 16, "xmax": 2560, "ymin": 1441, "ymax": 1534, "confidence": 0.9697242975234985, "label": "defect4"}]}, {"filename": "87.jpg", "rects": [{"xmin": 2118, "xmax": 2212, "ymin": 542, "ymax": 710, "confidence": 0.41593244671821594, "label": "defect9"}, {"xmin": 2192, "xmax": 2260, "ymin": 1614, "ymax": 1671, "confidence": 0.33753302693367004, "label": "defect9"}]}, {"filename": "447.jpg", "rects": [{"xmin": 0, "xmax": 2560, "ymin": 512, "ymax": 1169, "confidence": 0.9988973140716553, "label": "defect8"}]}, {"filename": "483.jpg", "rects": []}, {"filename": "59.jpg", "rects": [{"xmin": 0, "xmax": 2560, "ymin": 1156, "ymax": 1301, "confidence": 0.9989944100379944, "label": "defect4"}]}, {"filename": "177.jpg", "rects": [{"xmin": 0, "xmax": 2518, "ymin": 1737, "ymax": 1787, "confidence": 0.9999871253967285, "label": "defect7"}]}, {"filename": "441.jpg", "rects": [{"xmin": 0, "xmax": 2502, "ymin": 1604, "ymax": 1683, "confidence": 0.9353128671646118, "label": "defect7"}]}, {"filename": "37.jpg", "rects": [{"xmin": 0, "xmax": 2560, "ymin": 255, "ymax": 725, "confidence": 0.9564565420150757, "label": "defect3"}]}, {"filename": "8.jpg", "rects": [{"xmin": 0, "xmax": 2560, "ymin": 856, "ymax": 1633, "confidence": 0.9963333606719971, "label": "defect8"}]}, {"filename": "227.jpg", "rects": [{"xmin": 2070, "xmax": 2489, "ymin": 945, "ymax": 1122, "confidence": 0.8961685299873352, "label": "defect5"}, {"xmin": 2368, "xmax": 2438, "ymin": 643, "ymax": 694, "confidence": 0.311666876077652, "label": "defect9"}, {"xmin": 2145, "xmax": 2544, "ymin": 952, "ymax": 1180, "confidence": 0.3056788742542267, "label": "defect1"}]}, {"filename": "352.jpg", "rects": [{"xmin": 24, "xmax": 2557, "ymin": 1195, "ymax": 1343, "confidence": 0.9999622106552124, "label": "defect4"}]}, {"filename": "93.jpg", "rects": []}, {"filename": "28.jpg", "rects": [{"xmin": 4, "xmax": 2560, "ymin": 1026, "ymax": 1565, "confidence": 0.999235987663269, "label": "defect8"}]}, {"filename": "120.jpg", "rects": []}, {"filename": "412.jpg", "rects": [{"xmin": 95, "xmax": 1981, "ymin": 821, "ymax": 1102, "confidence": 0.4191916584968567, "label": "defect1"}]}, {"filename": "237.jpg", "rects": [{"xmin": 19, "xmax": 2546, "ymin": 846, "ymax": 1167, "confidence": 0.9999361038208008, "label": "defect0"}]}, {"filename": "404.jpg", "rects": [{"xmin": 0, "xmax": 2547, "ymin": 1002, "ymax": 1188, "confidence": 0.9999606609344482, "label": "defect4"}]}, {"filename": "266.jpg", "rects": []}, {"filename": "274.jpg", "rects": [{"xmin": 8, "xmax": 2560, "ymin": 1085, "ymax": 1731, "confidence": 0.9991236329078674, "label": "defect8"}]}, {"filename": "160.jpg", "rects": [{"xmin": 0, "xmax": 2560, "ymin": 623, "ymax": 944, "confidence": 0.999824583530426, "label": "defect8"}]}, {"filename": "345.jpg", "rects": [{"xmin": 908, "xmax": 1017, "ymin": 1266, "ymax": 1334, "confidence": 0.999991774559021, "label": "defect9"}, {"xmin": 28, "xmax": 2560, "ymin": 1009, "ymax": 1134, "confidence": 0.9978457689285278, "label": "defect2"}]}, {"filename": "429.jpg", "rects": [{"xmin": 8, "xmax": 2467, "ymin": 1144, "ymax": 1230, "confidence": 0.9998663663864136, "label": "defect4"}]}, {"filename": "205.jpg", "rects": [{"xmin": 4, "xmax": 2463, "ymin": 820, "ymax": 935, "confidence": 0.9782925248146057, "label": "defect2"}, {"xmin": 67, "xmax": 163, "ymin": 1161, "ymax": 1229, "confidence": 0.43877702951431274, "label": "defect9"}, {"xmin": 2390, "xmax": 2512, "ymin": 1092, "ymax": 1227, "confidence": 0.3454434871673584, "label": "defect9"}, {"xmin": 1577, "xmax": 1663, "ymin": 1062, "ymax": 1130, "confidence": 0.3355746269226074, "label": "defect9"}]}, {"filename": "165.jpg", "rects": []}, {"filename": "144.jpg", "rects": [{"xmin": 0, "xmax": 2538, "ymin": 872, "ymax": 1000, "confidence": 0.9989738464355469, "label": "defect4"}]}, {"filename": "384.jpg", "rects": [{"xmin": 0, "xmax": 2487, "ymin": 937, "ymax": 1009, "confidence": 0.9998427629470825, "label": "defect7"}]}, {"filename": "353.jpg", "rects": [{"xmin": 0, "xmax": 2557, "ymin": 779, "ymax": 1241, "confidence": 0.9997453093528748, "label": "defect0"}]}, {"filename": "486.jpg", "rects": []}, {"filename": "185.jpg", "rects": []}, {"filename": "403.jpg", "rects": [{"xmin": 0, "xmax": 2518, "ymin": 622, "ymax": 739, "confidence": 0.9995015859603882, "label": "defect7"}, {"xmin": 1301, "xmax": 1354, "ymin": 725, "ymax": 792, "confidence": 0.9355943202972412, "label": "defect1"}, {"xmin": 1293, "xmax": 1355, "ymin": 722, "ymax": 818, "confidence": 0.3547458052635193, "label": "defect9"}]}, {"filename": "247.jpg", "rects": [{"xmin": 0, "xmax": 2560, "ymin": 884, "ymax": 1125, "confidence": 0.9998633861541748, "label": "defect0"}]}, {"filename": "307.jpg", "rects": [{"xmin": 12, "xmax": 2560, "ymin": 161, "ymax": 248, "confidence": 0.903520405292511, "label": "defect3"}, {"xmin": 14, "xmax": 2521, "ymin": 132, "ymax": 311, "confidence": 0.7628451585769653, "label": "defect4"}]}, {"filename": "82.jpg", "rects": [{"xmin": 13, "xmax": 2560, "ymin": 1050, "ymax": 1173, "confidence": 0.9999524354934692, "label": "defect4"}]}, {"filename": "291.jpg", "rects": [{"xmin": 0, "xmax": 2527, "ymin": 1110, "ymax": 1407, "confidence": 0.9995844960212708, "label": "defect8"}]}, {"filename": "76.jpg", "rects": []}, {"filename": "437.jpg", "rects": [{"xmin": 0, "xmax": 2542, "ymin": 1224, "ymax": 1380, "confidence": 0.9999510049819946, "label": "defect2"}]}, {"filename": "411.jpg", "rects": [{"xmin": 7, "xmax": 2545, "ymin": 697, "ymax": 830, "confidence": 0.998885452747345, "label": "defect2"}]}, {"filename": "80.jpg", "rects": [{"xmin": 0, "xmax": 2539, "ymin": 198, "ymax": 276, "confidence": 0.99907386302948, "label": "defect3"}]}, {"filename": "373.jpg", "rects": []}, {"filename": "201.jpg", "rects": [{"xmin": 16, "xmax": 2530, "ymin": 849, "ymax": 1010, "confidence": 0.9771754741668701, "label": "defect0"}]}, {"filename": "226.jpg", "rects": []}, {"filename": "251.jpg", "rects": [{"xmin": 47, "xmax": 2560, "ymin": 636, "ymax": 917, "confidence": 0.9998594522476196, "label": "defect0"}]}, {"filename": "304.jpg", "rects": [{"xmin": 0, "xmax": 2560, "ymin": 540, "ymax": 951, "confidence": 0.9992139339447021, "label": "defect0"}]}, {"filename": "477.jpg", "rects": [{"xmin": 5, "xmax": 2548, "ymin": 580, "ymax": 704, "confidence": 0.999923825263977, "label": "defect2"}]}, {"filename": "462.jpg", "rects": [{"xmin": 156, "xmax": 2560, "ymin": 559, "ymax": 608, "confidence": 0.973660945892334, "label": "defect7"}, {"xmin": 169, "xmax": 237, "ymin": 449, "ymax": 501, "confidence": 0.3147212266921997, "label": "defect9"}]}, {"filename": "52.jpg", "rects": []}, {"filename": "310.jpg", "rects": [{"xmin": 15, "xmax": 2560, "ymin": 227, "ymax": 506, "confidence": 0.9987838864326477, "label": "defect3"}, {"xmin": 583, "xmax": 631, "ymin": 672, "ymax": 782, "confidence": 0.9946621060371399, "label": "defect9"}]}, {"filename": "51.jpg", "rects": [{"xmin": 22, "xmax": 2369, "ymin": 856, "ymax": 1260, "confidence": 0.9775591492652893, "label": "defect0"}]}, {"filename": "487.jpg", "rects": [{"xmin": 7, "xmax": 2560, "ymin": 911, "ymax": 1041, "confidence": 0.9999797344207764, "label": "defect2"}]}, {"filename": "298.jpg", "rects": []}, {"filename": "348.jpg", "rects": [{"xmin": 2, "xmax": 2560, "ymin": 772, "ymax": 1300, "confidence": 0.99968421459198, "label": "defect8"}]}, {"filename": "374.jpg", "rects": [{"xmin": 0, "xmax": 2560, "ymin": 1008, "ymax": 1583, "confidence": 0.9993294477462769, "label": "defect8"}, {"xmin": 925, "xmax": 982, "ymin": 1468, "ymax": 1514, "confidence": 0.43466541171073914, "label": "defect9"}, {"xmin": 561, "xmax": 663, "ymin": 1466, "ymax": 1536, "confidence": 0.35302403569221497, "label": "defect9"}]}, {"filename": "245.jpg", "rects": [{"xmin": 15, "xmax": 2560, "ymin": 863, "ymax": 997, "confidence": 0.9999700784683228, "label": "defect2"}, {"xmin": 2238, "xmax": 2355, "ymin": 1074, "ymax": 1129, "confidence": 0.5202669501304626, "label": "defect9"}]}, {"filename": "157.jpg", "rects": [{"xmin": 15, "xmax": 2560, "ymin": 930, "ymax": 1303, "confidence": 0.9998950958251953, "label": "defect0"}]}, {"filename": "485.jpg", "rects": [{"xmin": 151, "xmax": 2560, "ymin": 500, "ymax": 600, "confidence": 0.9987967014312744, "label": "defect7"}]}, {"filename": "35.jpg", "rects": [{"xmin": 0, "xmax": 2542, "ymin": 909, "ymax": 1073, "confidence": 0.9999666213989258, "label": "defect4"}]}, {"filename": "228.jpg", "rects": [{"xmin": 16, "xmax": 2532, "ymin": 765, "ymax": 889, "confidence": 0.9999425411224365, "label": "defect2"}, {"xmin": 2398, "xmax": 2535, "ymin": 1033, "ymax": 1183, "confidence": 0.6922035217285156, "label": "defect9"}, {"xmin": 2091, "xmax": 2261, "ymin": 1079, "ymax": 1186, "confidence": 0.5126502513885498, "label": "defect9"}, {"xmin": 580, "xmax": 666, "ymin": 1044, "ymax": 1109, "confidence": 0.3776644468307495, "label": "defect9"}]}, {"filename": "490.jpg", "rects": [{"xmin": 0, "xmax": 2544, "ymin": 984, "ymax": 1092, "confidence": 0.999549925327301, "label": "defect2"}, {"xmin": 2265, "xmax": 2558, "ymin": 1246, "ymax": 1449, "confidence": 0.4761311113834381, "label": "defect9"}]}, {"filename": "241.jpg", "rects": []}, {"filename": "109.jpg", "rects": []}, {"filename": "443.jpg", "rects": [{"xmin": 605, "xmax": 702, "ymin": 935, "ymax": 1019, "confidence": 0.3716755509376526, "label": "defect9"}]}, {"filename": "34.jpg", "rects": [{"xmin": 0, "xmax": 2549, "ymin": 874, "ymax": 1000, "confidence": 0.9999786615371704, "label": "defect2"}, {"xmin": 1317, "xmax": 1372, "ymin": 797, "ymax": 831, "confidence": 0.8841281533241272, "label": "defect9"}]}, {"filename": "359.jpg", "rects": [{"xmin": 12, "xmax": 2548, "ymin": 1317, "ymax": 1463, "confidence": 0.9987084865570068, "label": "defect2"}]}, {"filename": "178.jpg", "rects": [{"xmin": 66, "xmax": 2507, "ymin": 110, "ymax": 651, "confidence": 0.958361029624939, "label": "defect3"}, {"xmin": 2255, "xmax": 2317, "ymin": 355, "ymax": 478, "confidence": 0.32535290718078613, "label": "defect9"}, {"xmin": 31, "xmax": 521, "ymin": 83, "ymax": 164, "confidence": 0.31612062454223633, "label": "defect1"}]}, {"filename": "263.jpg", "rects": [{"xmin": 0, "xmax": 2556, "ymin": 667, "ymax": 1056, "confidence": 0.9999067783355713, "label": "defect0"}]}, {"filename": "203.jpg", "rects": [{"xmin": 0, "xmax": 2541, "ymin": 918, "ymax": 1288, "confidence": 0.9999942779541016, "label": "defect0"}]}, {"filename": "371.jpg", "rects": [{"xmin": 0, "xmax": 2560, "ymin": 676, "ymax": 1049, "confidence": 0.9999308586120605, "label": "defect0"}]}, {"filename": "182.jpg", "rects": [{"xmin": 0, "xmax": 2546, "ymin": 1002, "ymax": 1213, "confidence": 0.9999914169311523, "label": "defect4"}]}, {"filename": "380.jpg", "rects": [{"xmin": 1476, "xmax": 1536, "ymin": 255, "ymax": 307, "confidence": 0.9970300197601318, "label": "defect9"}, {"xmin": 0, "xmax": 2560, "ymin": 435, "ymax": 619, "confidence": 0.9969483017921448, "label": "defect3"}]}, {"filename": "33.jpg", "rects": []}, {"filename": "451.jpg", "rects": [{"xmin": 0, "xmax": 2544, "ymin": 1362, "ymax": 1498, "confidence": 0.9999604225158691, "label": "defect4"}, {"xmin": 512, "xmax": 572, "ymin": 1031, "ymax": 1075, "confidence": 0.9610315561294556, "label": "defect9"}]}, {"filename": "272.jpg", "rects": [{"xmin": 0, "xmax": 2560, "ymin": 1113, "ymax": 1235, "confidence": 0.9967101812362671, "label": "defect2"}, {"xmin": 0, "xmax": 1103, "ymin": 1234, "ymax": 1384, "confidence": 0.6312304139137268, "label": "defect9"}, {"xmin": 2410, "xmax": 2541, "ymin": 1417, "ymax": 1570, "confidence": 0.406174898147583, "label": "defect9"}]}, {"filename": "115.jpg", "rects": [{"xmin": 0, "xmax": 2560, "ymin": 553, "ymax": 967, "confidence": 0.9993553757667542, "label": "defect0"}]}, {"filename": "81.jpg", "rects": [{"xmin": 23, "xmax": 2436, "ymin": 1592, "ymax": 1673, "confidence": 0.996956467628479, "label": "defect4"}, {"xmin": 871, "xmax": 2004, "ymin": 1655, "ymax": 1858, "confidence": 0.46059927344322205, "label": "defect9"}, {"xmin": 614, "xmax": 671, "ymin": 1316, "ymax": 1357, "confidence": 0.31705668568611145, "label": "defect9"}]}, {"filename": "334.jpg", "rects": [{"xmin": 0, "xmax": 2557, "ymin": 712, "ymax": 848, "confidence": 0.9999685287475586, "label": "defect2"}, {"xmin": 1630, "xmax": 1746, "ymin": 946, "ymax": 1020, "confidence": 0.8873026371002197, "label": "defect9"}]}, {"filename": "44.jpg", "rects": []}, {"filename": "48.jpg", "rects": [{"xmin": 1625, "xmax": 1689, "ymin": 1054, "ymax": 1123, "confidence": 0.31287893652915955, "label": "defect9"}]}, {"filename": "254.jpg", "rects": [{"xmin": 0, "xmax": 2516, "ymin": 431, "ymax": 720, "confidence": 0.9970229268074036, "label": "defect8"}]}, {"filename": "78.jpg", "rects": [{"xmin": 6, "xmax": 2549, "ymin": 1248, "ymax": 1379, "confidence": 0.9999847412109375, "label": "defect4"}]}, {"filename": "341.jpg", "rects": [{"xmin": 0, "xmax": 2530, "ymin": 512, "ymax": 604, "confidence": 0.9692267179489136, "label": "defect3"}]}, {"filename": "440.jpg", "rects": [{"xmin": 0, "xmax": 2560, "ymin": 1223, "ymax": 1518, "confidence": 0.9992998838424683, "label": "defect8"}]}, {"filename": "204.jpg", "rects": [{"xmin": 12, "xmax": 2523, "ymin": 894, "ymax": 1014, "confidence": 0.9999035596847534, "label": "defect4"}]}, {"filename": "428.jpg", "rects": [{"xmin": 923, "xmax": 1236, "ymin": 806, "ymax": 1221, "confidence": 0.9909407496452332, "label": "defect0"}, {"xmin": 252, "xmax": 739, "ymin": 812, "ymax": 1004, "confidence": 0.41736704111099243, "label": "defect1"}]}, {"filename": "305.jpg", "rects": [{"xmin": 17, "xmax": 2560, "ymin": 1422, "ymax": 1555, "confidence": 0.9786417484283447, "label": "defect6"}]}, {"filename": "195.jpg", "rects": [{"xmin": 5, "xmax": 2543, "ymin": 1584, "ymax": 1706, "confidence": 0.9968603849411011, "label": "defect4"}]}, {"filename": "118.jpg", "rects": [{"xmin": 1190, "xmax": 1917, "ymin": 1777, "ymax": 1838, "confidence": 0.45635080337524414, "label": "defect1"}]}, {"filename": "326.jpg", "rects": [{"xmin": 1152, "xmax": 1212, "ymin": 1025, "ymax": 1070, "confidence": 0.9978228807449341, "label": "defect9"}, {"xmin": 2326, "xmax": 2477, "ymin": 1046, "ymax": 1181, "confidence": 0.42529019713401794, "label": "defect9"}, {"xmin": 22, "xmax": 2560, "ymin": 792, "ymax": 922, "confidence": 0.9970640540122986, "label": "defect2"}]}, {"filename": "133.jpg", "rects": [{"xmin": 491, "xmax": 685, "ymin": 1188, "ymax": 1292, "confidence": 0.9950147271156311, "label": "defect0"}, {"xmin": 0, "xmax": 43, "ymin": 1291, "ymax": 1335, "confidence": 0.4207732379436493, "label": "defect9"}]}, {"filename": "392.jpg", "rects": [{"xmin": 3, "xmax": 2552, "ymin": 967, "ymax": 1140, "confidence": 0.9839962124824524, "label": "defect4"}]}, {"filename": "398.jpg", "rects": [{"xmin": 0, "xmax": 2560, "ymin": 885, "ymax": 1501, "confidence": 0.9974009990692139, "label": "defect8"}]}, {"filename": "208.jpg", "rects": []}, {"filename": "381.jpg", "rects": [{"xmin": 7, "xmax": 2545, "ymin": 1049, "ymax": 1586, "confidence": 0.9995953440666199, "label": "defect8"}]}, {"filename": "496.jpg", "rects": [{"xmin": 0, "xmax": 2557, "ymin": 1308, "ymax": 1454, "confidence": 0.9985295534133911, "label": "defect4"}]}, {"filename": "98.jpg", "rects": [{"xmin": 51, "xmax": 2560, "ymin": 667, "ymax": 746, "confidence": 0.9998571872711182, "label": "defect7"}]}, {"filename": "346.jpg", "rects": [{"xmin": 0, "xmax": 2512, "ymin": 490, "ymax": 672, "confidence": 0.9836469292640686, "label": "defect3"}]}, {"filename": "101.jpg", "rects": [{"xmin": 0, "xmax": 2541, "ymin": 693, "ymax": 809, "confidence": 0.9991810917854309, "label": "defect2"}, {"xmin": 1178, "xmax": 1237, "ymin": 1061, "ymax": 1118, "confidence": 0.807666540145874, "label": "defect9"}, {"xmin": 597, "xmax": 747, "ymin": 1034, "ymax": 1132, "confidence": 0.46185338497161865, "label": "defect9"}, {"xmin": 2161, "xmax": 2459, "ymin": 933, "ymax": 1087, "confidence": 0.3150622248649597, "label": "defect9"}]}, {"filename": "61.jpg", "rects": [{"xmin": 0, "xmax": 2560, "ymin": 776, "ymax": 1401, "confidence": 0.8506146669387817, "label": "defect8"}]}, {"filename": "20.jpg", "rects": [{"xmin": 0, "xmax": 2560, "ymin": 1471, "ymax": 1569, "confidence": 0.9999918937683105, "label": "defect7"}]}, {"filename": "21.jpg", "rects": [{"xmin": 0, "xmax": 2548, "ymin": 951, "ymax": 1014, "confidence": 0.9992620348930359, "label": "defect7"}]}, {"filename": "360.jpg", "rects": [{"xmin": 9, "xmax": 2540, "ymin": 1038, "ymax": 1161, "confidence": 0.9999732971191406, "label": "defect4"}]}, {"filename": "489.jpg", "rects": [{"xmin": 0, "xmax": 2560, "ymin": 757, "ymax": 806, "confidence": 0.9980474710464478, "label": "defect7"}, {"xmin": 983, "xmax": 1037, "ymin": 1062, "ymax": 1111, "confidence": 0.5600423812866211, "label": "defect9"}]}, {"filename": "293.jpg", "rects": [{"xmin": 0, "xmax": 2547, "ymin": 1523, "ymax": 1599, "confidence": 0.9991016387939453, "label": "defect7"}]}, {"filename": "277.jpg", "rects": [{"xmin": 0, "xmax": 2560, "ymin": 1096, "ymax": 1188, "confidence": 0.9998781681060791, "label": "defect4"}]}, {"filename": "426.jpg", "rects": [{"xmin": 0, "xmax": 2422, "ymin": 1170, "ymax": 1252, "confidence": 0.9995139837265015, "label": "defect7"}]}, {"filename": "243.jpg", "rects": [{"xmin": 36, "xmax": 2560, "ymin": 245, "ymax": 355, "confidence": 0.970823347568512, "label": "defect3"}, {"xmin": 135, "xmax": 187, "ymin": 654, "ymax": 696, "confidence": 0.48442718386650085, "label": "defect9"}]}, {"filename": "265.jpg", "rects": [{"xmin": 0, "xmax": 2560, "ymin": 696, "ymax": 1368, "confidence": 0.9992570281028748, "label": "defect8"}]}, {"filename": "149.jpg", "rects": [{"xmin": 0, "xmax": 2557, "ymin": 1274, "ymax": 1394, "confidence": 0.9966462254524231, "label": "defect4"}]}, {"filename": "147.jpg", "rects": [{"xmin": 0, "xmax": 2554, "ymin": 1274, "ymax": 1378, "confidence": 0.9980475902557373, "label": "defect4"}, {"xmin": 1363, "xmax": 1442, "ymin": 809, "ymax": 875, "confidence": 0.5571390390396118, "label": "defect9"}]}, {"filename": "6.jpg", "rects": []}, {"filename": "338.jpg", "rects": [{"xmin": 37, "xmax": 2547, "ymin": 777, "ymax": 831, "confidence": 0.9999935626983643, "label": "defect7"}]}, {"filename": "375.jpg", "rects": [{"xmin": 0, "xmax": 2332, "ymin": 1465, "ymax": 1570, "confidence": 0.9989738464355469, "label": "defect4"}]}, {"filename": "261.jpg", "rects": [{"xmin": 16, "xmax": 2560, "ymin": 864, "ymax": 1008, "confidence": 0.9999730587005615, "label": "defect2"}, {"xmin": 41, "xmax": 435, "ymin": 1156, "ymax": 1376, "confidence": 0.8424802422523499, "label": "defect9"}]}, {"filename": "19.jpg", "rects": []}, {"filename": "23.jpg", "rects": [{"xmin": 119, "xmax": 2499, "ymin": 1501, "ymax": 1638, "confidence": 0.7111001014709473, "label": "defect2"}]}, {"filename": "414.jpg", "rects": [{"xmin": 25, "xmax": 2539, "ymin": 794, "ymax": 1217, "confidence": 0.9945467710494995, "label": "defect8"}]}, {"filename": "183.jpg", "rects": [{"xmin": 0, "xmax": 2560, "ymin": 848, "ymax": 1311, "confidence": 0.999850869178772, "label": "defect0"}]}, {"filename": "145.jpg", "rects": [{"xmin": 8, "xmax": 2560, "ymin": 418, "ymax": 606, "confidence": 0.9990992546081543, "label": "defect3"}]}, {"filename": "2.jpg", "rects": [{"xmin": 0, "xmax": 2550, "ymin": 341, "ymax": 509, "confidence": 0.9295843243598938, "label": "defect3"}, {"xmin": 450, "xmax": 514, "ymin": 180, "ymax": 229, "confidence": 0.5410584211349487, "label": "defect9"}]}, {"filename": "105.jpg", "rects": [{"xmin": 6, "xmax": 2560, "ymin": 614, "ymax": 1258, "confidence": 0.9969844222068787, "label": "defect8"}]}, {"filename": "152.jpg", "rects": [{"xmin": 0, "xmax": 2560, "ymin": 821, "ymax": 1594, "confidence": 0.9975704550743103, "label": "defect8"}, {"xmin": 1321, "xmax": 1387, "ymin": 1210, "ymax": 1259, "confidence": 0.32599663734436035, "label": "defect9"}, {"xmin": 2421, "xmax": 2507, "ymin": 913, "ymax": 975, "confidence": 0.31658098101615906, "label": "defect9"}]}, {"filename": "459.jpg", "rects": [{"xmin": 0, "xmax": 2560, "ymin": 751, "ymax": 1101, "confidence": 0.9998372793197632, "label": "defect0"}]}, {"filename": "407.jpg", "rects": [{"xmin": 4, "xmax": 2555, "ymin": 1206, "ymax": 1286, "confidence": 0.9939025640487671, "label": "defect4"}]}, {"filename": "377.jpg", "rects": [{"xmin": 152, "xmax": 2432, "ymin": 919, "ymax": 1303, "confidence": 0.986604630947113, "label": "defect1"}]}, {"filename": "453.jpg", "rects": [{"xmin": 310, "xmax": 370, "ymin": 800, "ymax": 851, "confidence": 0.9999370574951172, "label": "defect9"}, {"xmin": 9, "xmax": 2560, "ymin": 1530, "ymax": 1749, "confidence": 0.7805856466293335, "label": "defect2"}]}, {"filename": "10.jpg", "rects": [{"xmin": 0, "xmax": 2557, "ymin": 960, "ymax": 1312, "confidence": 0.9995290040969849, "label": "defect0"}]}, {"filename": "140.jpg", "rects": [{"xmin": 0, "xmax": 2560, "ymin": 544, "ymax": 1034, "confidence": 0.9998255372047424, "label": "defect0"}]}, {"filename": "284.jpg", "rects": [{"xmin": 0, "xmax": 2466, "ymin": 193, "ymax": 264, "confidence": 0.9942651391029358, "label": "defect3"}]}, {"filename": "361.jpg", "rects": [{"xmin": 49, "xmax": 2560, "ymin": 1148, "ymax": 1238, "confidence": 0.9998995065689087, "label": "defect4"}]}, {"filename": "194.jpg", "rects": [{"xmin": 1354, "xmax": 2288, "ymin": 1695, "ymax": 1818, "confidence": 0.9951165914535522, "label": "defect0"}]}, {"filename": "161.jpg", "rects": [{"xmin": 62, "xmax": 2560, "ymin": 1233, "ymax": 1549, "confidence": 0.9904116988182068, "label": "defect8"}]}, {"filename": "340.jpg", "rects": [{"xmin": 5, "xmax": 2560, "ymin": 807, "ymax": 1185, "confidence": 0.9999814033508301, "label": "defect0"}]}, {"filename": "100.jpg", "rects": [{"xmin": 44, "xmax": 2560, "ymin": 1195, "ymax": 1276, "confidence": 0.9776971340179443, "label": "defect7"}]}, {"filename": "449.jpg", "rects": [{"xmin": 0, "xmax": 2560, "ymin": 834, "ymax": 1175, "confidence": 0.9983295798301697, "label": "defect8"}]}, {"filename": "297.jpg", "rects": [{"xmin": 960, "xmax": 2341, "ymin": 1290, "ymax": 1432, "confidence": 0.9895780086517334, "label": "defect0"}]}, {"filename": "126.jpg", "rects": [{"xmin": 0, "xmax": 2538, "ymin": 887, "ymax": 1431, "confidence": 0.9989405274391174, "label": "defect8"}]}, {"filename": "64.jpg", "rects": [{"xmin": 5, "xmax": 2560, "ymin": 922, "ymax": 1022, "confidence": 0.9999370574951172, "label": "defect4"}]}, {"filename": "491.jpg", "rects": [{"xmin": 0, "xmax": 2544, "ymin": 582, "ymax": 960, "confidence": 0.9997989535331726, "label": "defect0"}]}, {"filename": "151.jpg", "rects": [{"xmin": 0, "xmax": 2543, "ymin": 1271, "ymax": 1892, "confidence": 0.9920253753662109, "label": "defect8"}]}, {"filename": "191.jpg", "rects": [{"xmin": 13, "xmax": 2539, "ymin": 623, "ymax": 1140, "confidence": 0.9965057373046875, "label": "defect8"}]}, {"filename": "111.jpg", "rects": []}, {"filename": "435.jpg", "rects": [{"xmin": 2006, "xmax": 2170, "ymin": 1038, "ymax": 1238, "confidence": 0.9935812950134277, "label": "defect1"}, {"xmin": 1989, "xmax": 2151, "ymin": 1052, "ymax": 1234, "confidence": 0.7050269246101379, "label": "defect9"}]}, {"filename": "413.jpg", "rects": [{"xmin": 0, "xmax": 2458, "ymin": 1085, "ymax": 1455, "confidence": 0.9653375744819641, "label": "defect5"}]}, {"filename": "286.jpg", "rects": []}, {"filename": "327.jpg", "rects": [{"xmin": 0, "xmax": 2560, "ymin": 1107, "ymax": 1215, "confidence": 0.9997066855430603, "label": "defect4"}, {"xmin": 678, "xmax": 755, "ymin": 658, "ymax": 717, "confidence": 0.7406896352767944, "label": "defect9"}]}, {"filename": "58.jpg", "rects": []}, {"filename": "301.jpg", "rects": [{"xmin": 14, "xmax": 2554, "ymin": 691, "ymax": 1068, "confidence": 0.9998869895935059, "label": "defect0"}]}, {"filename": "287.jpg", "rects": [{"xmin": 885, "xmax": 2455, "ymin": 1558, "ymax": 1663, "confidence": 0.9801174998283386, "label": "defect6"}]}, {"filename": "218.jpg", "rects": [{"xmin": 0, "xmax": 2549, "ymin": 1479, "ymax": 1614, "confidence": 0.9981305003166199, "label": "defect4"}]}, {"filename": "209.jpg", "rects": [{"xmin": 21, "xmax": 2560, "ymin": 1178, "ymax": 1303, "confidence": 0.999387264251709, "label": "defect4"}, {"xmin": 843, "xmax": 1417, "ymin": 1043, "ymax": 1104, "confidence": 0.4757806956768036, "label": "defect9"}]}, {"filename": "212.jpg", "rects": [{"xmin": 13, "xmax": 2560, "ymin": 998, "ymax": 1132, "confidence": 0.9965009689331055, "label": "defect2"}]}, {"filename": "418.jpg", "rects": [{"xmin": 854, "xmax": 1124, "ymin": 1278, "ymax": 1547, "confidence": 0.5804039239883423, "label": "defect9"}, {"xmin": 427, "xmax": 495, "ymin": 786, "ymax": 860, "confidence": 0.3450890779495239, "label": "defect9"}]}, {"filename": "494.jpg", "rects": [{"xmin": 13, "xmax": 2560, "ymin": 738, "ymax": 1112, "confidence": 0.9999657869338989, "label": "defect0"}]}, {"filename": "256.jpg", "rects": [{"xmin": 0, "xmax": 2533, "ymin": 1365, "ymax": 1447, "confidence": 0.9982690811157227, "label": "defect4"}]}, {"filename": "480.jpg", "rects": []}, {"filename": "5.jpg", "rects": [{"xmin": 1374, "xmax": 1423, "ymin": 369, "ymax": 416, "confidence": 0.9991782307624817, "label": "defect9"}, {"xmin": 1226, "xmax": 1279, "ymin": 352, "ymax": 398, "confidence": 0.73683100938797, "label": "defect9"}, {"xmin": 34, "xmax": 2519, "ymin": 869, "ymax": 995, "confidence": 0.8684014081954956, "label": "defect7"}, {"xmin": 2083, "xmax": 2154, "ymin": 450, "ymax": 564, "confidence": 0.3817498981952667, "label": "defect1"}]}, {"filename": "31.jpg", "rects": [{"xmin": 0, "xmax": 2537, "ymin": 851, "ymax": 973, "confidence": 0.9859200716018677, "label": "defect2"}, {"xmin": 1765, "xmax": 1954, "ymin": 1119, "ymax": 1208, "confidence": 0.6914145946502686, "label": "defect9"}, {"xmin": 2422, "xmax": 2550, "ymin": 1073, "ymax": 1259, "confidence": 0.33657339215278625, "label": "defect9"}, {"xmin": 222, "xmax": 364, "ymin": 1041, "ymax": 1118, "confidence": 0.30032220482826233, "label": "defect9"}]}, {"filename": "369.jpg", "rects": [{"xmin": 10, "xmax": 2560, "ymin": 467, "ymax": 1106, "confidence": 0.9996182918548584, "label": "defect8"}]}, {"filename": "465.jpg", "rects": [{"xmin": 0, "xmax": 2557, "ymin": 199, "ymax": 401, "confidence": 0.9964847564697266, "label": "defect3"}, {"xmin": 585, "xmax": 647, "ymin": 694, "ymax": 751, "confidence": 0.3038857579231262, "label": "defect9"}]}, {"filename": "0.jpg", "rects": [{"xmin": 0, "xmax": 2547, "ymin": 578, "ymax": 892, "confidence": 0.9996453523635864, "label": "defect8"}]}, {"filename": "499.jpg", "rects": []}, {"filename": "235.jpg", "rects": [{"xmin": 25, "xmax": 2544, "ymin": 632, "ymax": 1238, "confidence": 0.9987565279006958, "label": "defect8"}]}, {"filename": "478.jpg", "rects": [{"xmin": 93, "xmax": 2560, "ymin": 867, "ymax": 919, "confidence": 0.9994838237762451, "label": "defect7"}]}, {"filename": "127.jpg", "rects": []}, {"filename": "49.jpg", "rects": [{"xmin": 22, "xmax": 2550, "ymin": 1274, "ymax": 1571, "confidence": 0.9994199275970459, "label": "defect8"}]}, {"filename": "242.jpg", "rects": [{"xmin": 30, "xmax": 2555, "ymin": 1213, "ymax": 1329, "confidence": 0.9991661310195923, "label": "defect4"}, {"xmin": 2028, "xmax": 2092, "ymin": 746, "ymax": 807, "confidence": 0.5597482919692993, "label": "defect9"}, {"xmin": 73, "xmax": 161, "ymin": 1132, "ymax": 1204, "confidence": 0.42886707186698914, "label": "defect9"}]}, {"filename": "176.jpg", "rects": [{"xmin": 1693, "xmax": 1779, "ymin": 1527, "ymax": 1586, "confidence": 0.9696499109268188, "label": "defect6"}, {"xmin": 458, "xmax": 536, "ymin": 1553, "ymax": 1604, "confidence": 0.9430271983146667, "label": "defect9"}]}, {"filename": "368.jpg", "rects": [{"xmin": 0, "xmax": 2554, "ymin": 853, "ymax": 979, "confidence": 0.9981361627578735, "label": "defect2"}, {"xmin": 245, "xmax": 669, "ymin": 996, "ymax": 1104, "confidence": 0.9419731497764587, "label": "defect9"}, {"xmin": 2366, "xmax": 2521, "ymin": 1100, "ymax": 1277, "confidence": 0.4106423556804657, "label": "defect9"}, {"xmin": 949, "xmax": 1016, "ymin": 1196, "ymax": 1249, "confidence": 0.3064658045768738, "label": "defect9"}]}, {"filename": "255.jpg", "rects": []}, {"filename": "13.jpg", "rects": [{"xmin": 10, "xmax": 2560, "ymin": 1083, "ymax": 1251, "confidence": 0.9999197721481323, "label": "defect4"}]}, {"filename": "73.jpg", "rects": [{"xmin": 0, "xmax": 2548, "ymin": 1287, "ymax": 1357, "confidence": 0.951555073261261, "label": "defect7"}]}, {"filename": "300.jpg", "rects": []}, {"filename": "236.jpg", "rects": []}, {"filename": "92.jpg", "rects": [{"xmin": 1343, "xmax": 1432, "ymin": 1519, "ymax": 1585, "confidence": 0.9999817609786987, "label": "defect9"}, {"xmin": 972, "xmax": 1041, "ymin": 953, "ymax": 1074, "confidence": 0.30702605843544006, "label": "defect9"}]}, {"filename": "18.jpg", "rects": [{"xmin": 1640, "xmax": 1720, "ymin": 1371, "ymax": 1429, "confidence": 1.0, "label": "defect9"}, {"xmin": 1263, "xmax": 1342, "ymin": 1799, "ymax": 1859, "confidence": 0.41244223713874817, "label": "defect9"}, {"xmin": 86, "xmax": 660, "ymin": 241, "ymax": 297, "confidence": 0.42023831605911255, "label": "defect1"}]}, {"filename": "319.jpg", "rects": [{"xmin": 1, "xmax": 2560, "ymin": 1229, "ymax": 1344, "confidence": 0.9999016523361206, "label": "defect4"}]}, {"filename": "54.jpg", "rects": [{"xmin": 2, "xmax": 2560, "ymin": 969, "ymax": 1011, "confidence": 0.7480947375297546, "label": "defect7"}, {"xmin": 0, "xmax": 350, "ymin": 609, "ymax": 920, "confidence": 0.5563759207725525, "label": "defect9"}]}, {"filename": "323.jpg", "rects": [{"xmin": 1, "xmax": 2560, "ymin": 1007, "ymax": 1121, "confidence": 0.9615330100059509, "label": "defect2"}]}, {"filename": "337.jpg", "rects": []}, {"filename": "108.jpg", "rects": []}, {"filename": "391.jpg", "rects": [{"xmin": 49, "xmax": 2540, "ymin": 790, "ymax": 1178, "confidence": 0.9997097849845886, "label": "defect0"}]}, {"filename": "166.jpg", "rects": [{"xmin": 19, "xmax": 2560, "ymin": 999, "ymax": 1129, "confidence": 0.9946908354759216, "label": "defect2"}]}, {"filename": "456.jpg", "rects": [{"xmin": 0, "xmax": 2554, "ymin": 648, "ymax": 712, "confidence": 0.9733549952507019, "label": "defect7"}]}, {"filename": "317.jpg", "rects": [{"xmin": 0, "xmax": 2560, "ymin": 835, "ymax": 1241, "confidence": 0.9979255199432373, "label": "defect8"}]}, {"filename": "55.jpg", "rects": [{"xmin": 6, "xmax": 2560, "ymin": 213, "ymax": 287, "confidence": 0.9985219836235046, "label": "defect3"}, {"xmin": 418, "xmax": 510, "ymin": 788, "ymax": 873, "confidence": 0.9825679659843445, "label": "defect9"}]}, {"filename": "27.jpg", "rects": [{"xmin": 61, "xmax": 2539, "ymin": 792, "ymax": 1182, "confidence": 0.9817018508911133, "label": "defect0"}, {"xmin": 51, "xmax": 2384, "ymin": 1716, "ymax": 1804, "confidence": 0.814516544342041, "label": "defect0"}, {"xmin": 1767, "xmax": 1837, "ymin": 1624, "ymax": 1680, "confidence": 0.6113907098770142, "label": "defect9"}, {"xmin": 2111, "xmax": 2234, "ymin": 1531, "ymax": 1608, "confidence": 0.40665799379348755, "label": "defect9"}, {"xmin": 125, "xmax": 1434, "ymin": 1700, "ymax": 1808, "confidence": 0.562524139881134, "label": "defect1"}]}, {"filename": "308.jpg", "rects": [{"xmin": 10, "xmax": 2546, "ymin": 957, "ymax": 1021, "confidence": 0.9983539581298828, "label": "defect7"}]}, {"filename": "137.jpg", "rects": [{"xmin": 3, "xmax": 2560, "ymin": 660, "ymax": 976, "confidence": 0.9998687505722046, "label": "defect0"}]}, {"filename": "71.jpg", "rects": [{"xmin": 11, "xmax": 2560, "ymin": 707, "ymax": 884, "confidence": 0.9999895095825195, "label": "defect2"}]}, {"filename": "45.jpg", "rects": [{"xmin": 48, "xmax": 2514, "ymin": 1058, "ymax": 1822, "confidence": 0.9959166646003723, "label": "defect8"}]}, {"filename": "154.jpg", "rects": []}, {"filename": "320.jpg", "rects": [{"xmin": 0, "xmax": 2467, "ymin": 1402, "ymax": 1523, "confidence": 0.9687801003456116, "label": "defect1"}]}, {"filename": "129.jpg", "rects": [{"xmin": 0, "xmax": 2478, "ymin": 1022, "ymax": 1091, "confidence": 0.9991088509559631, "label": "defect7"}]}, {"filename": "188.jpg", "rects": [{"xmin": 0, "xmax": 2556, "ymin": 918, "ymax": 1039, "confidence": 0.999985933303833, "label": "defect2"}, {"xmin": 415, "xmax": 514, "ymin": 1183, "ymax": 1228, "confidence": 0.8522457480430603, "label": "defect9"}, {"xmin": 1046, "xmax": 1109, "ymin": 1323, "ymax": 1372, "confidence": 0.6383762359619141, "label": "defect9"}, {"xmin": 894, "xmax": 1102, "ymin": 1051, "ymax": 1155, "confidence": 0.40038612484931946, "label": "defect9"}]}, {"filename": "257.jpg", "rects": []}, {"filename": "365.jpg", "rects": [{"xmin": 17, "xmax": 2560, "ymin": 780, "ymax": 1139, "confidence": 0.9999915361404419, "label": "defect0"}]}, {"filename": "290.jpg", "rects": [{"xmin": 39, "xmax": 2520, "ymin": 1574, "ymax": 1741, "confidence": 0.7609993815422058, "label": "defect4"}]}, {"filename": "270.jpg", "rects": [{"xmin": 6, "xmax": 2548, "ymin": 886, "ymax": 1057, "confidence": 0.9999961853027344, "label": "defect4"}]}, {"filename": "455.jpg", "rects": [{"xmin": 24, "xmax": 2560, "ymin": 1231, "ymax": 1399, "confidence": 0.9999951124191284, "label": "defect2"}, {"xmin": 2248, "xmax": 2312, "ymin": 1120, "ymax": 1168, "confidence": 0.6476757526397705, "label": "defect9"}]}, {"filename": "390.jpg", "rects": []}, {"filename": "349.jpg", "rects": [{"xmin": 8, "xmax": 2540, "ymin": 590, "ymax": 790, "confidence": 0.9981448650360107, "label": "defect2"}]}, {"filename": "267.jpg", "rects": [{"xmin": 9, "xmax": 2553, "ymin": 1158, "ymax": 1286, "confidence": 0.9968906044960022, "label": "defect2"}, {"xmin": 1025, "xmax": 1097, "ymin": 1407, "ymax": 1449, "confidence": 0.9091730713844299, "label": "defect9"}]}, {"filename": "229.jpg", "rects": [{"xmin": 735, "xmax": 787, "ymin": 721, "ymax": 760, "confidence": 0.9912051558494568, "label": "defect9"}, {"xmin": 1754, "xmax": 2003, "ymin": 700, "ymax": 882, "confidence": 0.3149759769439697, "label": "defect9"}]}, {"filename": "498.jpg", "rects": [{"xmin": 747, "xmax": 2501, "ymin": 1332, "ymax": 1614, "confidence": 0.994282603263855, "label": "defect5"}]}, {"filename": "132.jpg", "rects": [{"xmin": 304, "xmax": 2560, "ymin": 1151, "ymax": 1261, "confidence": 0.9932267069816589, "label": "defect2"}, {"xmin": 158, "xmax": 295, "ymin": 1508, "ymax": 1594, "confidence": 0.41406333446502686, "label": "defect9"}, {"xmin": 858, "xmax": 1001, "ymin": 1351, "ymax": 1440, "confidence": 0.36834716796875, "label": "defect9"}, {"xmin": 100, "xmax": 316, "ymin": 1301, "ymax": 1416, "confidence": 0.33614829182624817, "label": "defect9"}]}, {"filename": "395.jpg", "rects": [{"xmin": 11, "xmax": 2560, "ymin": 451, "ymax": 1092, "confidence": 0.9993113279342651, "label": "defect8"}]}, {"filename": "173.jpg", "rects": []}, {"filename": "366.jpg", "rects": []}, {"filename": "269.jpg", "rects": [{"xmin": 0, "xmax": 2556, "ymin": 909, "ymax": 1289, "confidence": 0.9999817609786987, "label": "defect0"}]}, {"filename": "252.jpg", "rects": []}, {"filename": "430.jpg", "rects": [{"xmin": 2126, "xmax": 2189, "ymin": 542, "ymax": 607, "confidence": 0.9038112163543701, "label": "defect9"}, {"xmin": 1086, "xmax": 1379, "ymin": 1042, "ymax": 1212, "confidence": 0.7821738719940186, "label": "defect5"}]}, {"filename": "72.jpg", "rects": [{"xmin": 1273, "xmax": 1358, "ymin": 1058, "ymax": 1115, "confidence": 0.9991680383682251, "label": "defect9"}]}, {"filename": "314.jpg", "rects": [{"xmin": 2451, "xmax": 2501, "ymin": 780, "ymax": 832, "confidence": 0.4876212179660797, "label": "defect9"}]}, {"filename": "306.jpg", "rects": [{"xmin": 7, "xmax": 2560, "ymin": 1005, "ymax": 1178, "confidence": 0.9998685121536255, "label": "defect4"}]}, {"filename": "79.jpg", "rects": [{"xmin": 2, "xmax": 2560, "ymin": 715, "ymax": 1012, "confidence": 0.9970600008964539, "label": "defect8"}]}, {"filename": "281.jpg", "rects": []}, {"filename": "168.jpg", "rects": [{"xmin": 21, "xmax": 2556, "ymin": 583, "ymax": 653, "confidence": 0.999382495880127, "label": "defect7"}]}, {"filename": "155.jpg", "rects": []}, {"filename": "57.jpg", "rects": []}, {"filename": "222.jpg", "rects": []}, {"filename": "397.jpg", "rects": [{"xmin": 6, "xmax": 2560, "ymin": 519, "ymax": 735, "confidence": 0.9891505837440491, "label": "defect2"}]}, {"filename": "362.jpg", "rects": [{"xmin": 9, "xmax": 120, "ymin": 1665, "ymax": 1729, "confidence": 0.80804443359375, "label": "defect6"}]}, {"filename": "406.jpg", "rects": [{"xmin": 2, "xmax": 2560, "ymin": 158, "ymax": 228, "confidence": 0.9747998714447021, "label": "defect3"}]}, {"filename": "174.jpg", "rects": [{"xmin": 9, "xmax": 2552, "ymin": 1099, "ymax": 1617, "confidence": 0.9979382157325745, "label": "defect8"}]}, {"filename": "136.jpg", "rects": [{"xmin": 1482, "xmax": 1553, "ymin": 819, "ymax": 874, "confidence": 0.9999748468399048, "label": "defect9"}, {"xmin": 545, "xmax": 604, "ymin": 554, "ymax": 610, "confidence": 0.49873048067092896, "label": "defect9"}, {"xmin": 2242, "xmax": 2300, "ymin": 611, "ymax": 660, "confidence": 0.3288377523422241, "label": "defect9"}]}, {"filename": "383.jpg", "rects": [{"xmin": 10, "xmax": 2543, "ymin": 828, "ymax": 1154, "confidence": 0.9997058510780334, "label": "defect0"}]}, {"filename": "231.jpg", "rects": [{"xmin": 1246, "xmax": 1300, "ymin": 1210, "ymax": 1255, "confidence": 0.9884825348854065, "label": "defect9"}, {"xmin": 615, "xmax": 669, "ymin": 1134, "ymax": 1188, "confidence": 0.4529796838760376, "label": "defect9"}, {"xmin": 62, "xmax": 2560, "ymin": 1007, "ymax": 1314, "confidence": 0.638973593711853, "label": "defect0"}]}, {"filename": "11.jpg", "rects": []}, {"filename": "248.jpg", "rects": [{"xmin": 2, "xmax": 2556, "ymin": 703, "ymax": 839, "confidence": 0.9999079704284668, "label": "defect2"}]}, {"filename": "476.jpg", "rects": [{"xmin": 0, "xmax": 2537, "ymin": 1191, "ymax": 1802, "confidence": 0.9985437393188477, "label": "defect8"}]}, {"filename": "311.jpg", "rects": [{"xmin": 119, "xmax": 2560, "ymin": 1241, "ymax": 1342, "confidence": 0.9999028444290161, "label": "defect4"}]}, {"filename": "107.jpg", "rects": [{"xmin": 279, "xmax": 2560, "ymin": 1162, "ymax": 1270, "confidence": 0.9933257102966309, "label": "defect4"}]}, {"filename": "303.jpg", "rects": [{"xmin": 1905, "xmax": 2372, "ymin": 1362, "ymax": 1520, "confidence": 0.7913510799407959, "label": "defect5"}]}, {"filename": "328.jpg", "rects": [{"xmin": 0, "xmax": 2560, "ymin": 1727, "ymax": 1787, "confidence": 0.9999690055847168, "label": "defect7"}]}, {"filename": "26.jpg", "rects": [{"xmin": 0, "xmax": 2557, "ymin": 1232, "ymax": 1345, "confidence": 0.9996460676193237, "label": "defect4"}]}, {"filename": "169.jpg", "rects": [{"xmin": 0, "xmax": 2519, "ymin": 935, "ymax": 1260, "confidence": 0.9993915557861328, "label": "defect4"}]}, {"filename": "17.jpg", "rects": [{"xmin": 26, "xmax": 2553, "ymin": 797, "ymax": 1110, "confidence": 0.999995231628418, "label": "defect0"}]}, {"filename": "250.jpg", "rects": []}, {"filename": "421.jpg", "rects": [{"xmin": 3, "xmax": 2560, "ymin": 587, "ymax": 978, "confidence": 0.9996546506881714, "label": "defect0"}]}, {"filename": "488.jpg", "rects": [{"xmin": 21, "xmax": 2560, "ymin": 1076, "ymax": 1269, "confidence": 0.9998986721038818, "label": "defect4"}]}, {"filename": "192.jpg", "rects": [{"xmin": 324, "xmax": 421, "ymin": 1087, "ymax": 1144, "confidence": 0.895442008972168, "label": "defect9"}]}, {"filename": "4.jpg", "rects": [{"xmin": 0, "xmax": 2549, "ymin": 1180, "ymax": 1370, "confidence": 0.9999262094497681, "label": "defect4"}]}, {"filename": "70.jpg", "rects": [{"xmin": 937, "xmax": 1010, "ymin": 995, "ymax": 1053, "confidence": 0.9999947547912598, "label": "defect9"}, {"xmin": 76, "xmax": 146, "ymin": 1037, "ymax": 1084, "confidence": 0.45125842094421387, "label": "defect9"}, {"xmin": 1029, "xmax": 1091, "ymin": 1784, "ymax": 1828, "confidence": 0.8883471488952637, "label": "defect6"}]}, {"filename": "9.jpg", "rects": [{"xmin": 0, "xmax": 2554, "ymin": 474, "ymax": 870, "confidence": 0.9999518394470215, "label": "defect0"}]}, {"filename": "460.jpg", "rects": []}, {"filename": "90.jpg", "rects": [{"xmin": 12, "xmax": 2558, "ymin": 1110, "ymax": 1236, "confidence": 0.9964060187339783, "label": "defect4"}]}, {"filename": "104.jpg", "rects": [{"xmin": 5, "xmax": 2560, "ymin": 1358, "ymax": 1507, "confidence": 0.9999785423278809, "label": "defect2"}]}, {"filename": "273.jpg", "rects": [{"xmin": 0, "xmax": 2560, "ymin": 1510, "ymax": 1642, "confidence": 0.9999746084213257, "label": "defect4"}, {"xmin": 500, "xmax": 1536, "ymin": 1639, "ymax": 1733, "confidence": 0.9237578511238098, "label": "defect9"}]}, {"filename": "249.jpg", "rects": [{"xmin": 0, "xmax": 2560, "ymin": 1028, "ymax": 1146, "confidence": 0.9999006986618042, "label": "defect2"}, {"xmin": 66, "xmax": 152, "ymin": 1193, "ymax": 1249, "confidence": 0.3572808802127838, "label": "defect9"}, {"xmin": 2324, "xmax": 2547, "ymin": 1137, "ymax": 1277, "confidence": 0.32095301151275635, "label": "defect9"}]}, {"filename": "350.jpg", "rects": [{"xmin": 11, "xmax": 2560, "ymin": 528, "ymax": 892, "confidence": 0.9976086616516113, "label": "defect8"}]}, {"filename": "351.jpg", "rects": [{"xmin": 82, "xmax": 2560, "ymin": 672, "ymax": 776, "confidence": 0.9983674883842468, "label": "defect7"}, {"xmin": 750, "xmax": 966, "ymin": 713, "ymax": 795, "confidence": 0.9209011197090149, "label": "defect1"}]}, {"filename": "475.jpg", "rects": [{"xmin": 62, "xmax": 2560, "ymin": 788, "ymax": 829, "confidence": 0.9999954700469971, "label": "defect7"}]}, {"filename": "400.jpg", "rects": [{"xmin": 25, "xmax": 2522, "ymin": 1564, "ymax": 1676, "confidence": 0.9961398243904114, "label": "defect4"}]}, {"filename": "123.jpg", "rects": [{"xmin": 39, "xmax": 2560, "ymin": 861, "ymax": 1255, "confidence": 0.9993575215339661, "label": "defect8"}]}, {"filename": "244.jpg", "rects": [{"xmin": 0, "xmax": 2547, "ymin": 921, "ymax": 974, "confidence": 0.9994519352912903, "label": "defect7"}, {"xmin": 1424, "xmax": 1486, "ymin": 755, "ymax": 804, "confidence": 0.32894304394721985, "label": "defect9"}]}, {"filename": "433.jpg", "rects": [{"xmin": 83, "xmax": 2539, "ymin": 983, "ymax": 1727, "confidence": 0.9977846741676331, "label": "defect8"}]}, {"filename": "1.jpg", "rects": [{"xmin": 96, "xmax": 2560, "ymin": 829, "ymax": 991, "confidence": 0.9947502017021179, "label": "defect2"}]}, {"filename": "116.jpg", "rects": []}, {"filename": "207.jpg", "rects": [{"xmin": 19, "xmax": 2560, "ymin": 1351, "ymax": 1499, "confidence": 0.9999958276748657, "label": "defect4"}]}, {"filename": "295.jpg", "rects": [{"xmin": 36, "xmax": 2534, "ymin": 1236, "ymax": 1563, "confidence": 0.9964730143547058, "label": "defect0"}, {"xmin": 1419, "xmax": 1460, "ymin": 1557, "ymax": 1593, "confidence": 0.35166487097740173, "label": "defect1"}, {"xmin": 1415, "xmax": 1465, "ymin": 1550, "ymax": 1599, "confidence": 0.3099113702774048, "label": "defect9"}]}, {"filename": "385.jpg", "rects": []}, {"filename": "83.jpg", "rects": [{"xmin": 14, "xmax": 2560, "ymin": 927, "ymax": 1027, "confidence": 0.999863862991333, "label": "defect7"}]}, {"filename": "302.jpg", "rects": []}, {"filename": "446.jpg", "rects": [{"xmin": 0, "xmax": 2511, "ymin": 1366, "ymax": 1463, "confidence": 0.9998118281364441, "label": "defect4"}]}, {"filename": "85.jpg", "rects": [{"xmin": 46, "xmax": 2560, "ymin": 838, "ymax": 1002, "confidence": 0.9997566342353821, "label": "defect4"}]}, {"filename": "67.jpg", "rects": []}, {"filename": "215.jpg", "rects": []}, {"filename": "332.jpg", "rects": [{"xmin": 6, "xmax": 2523, "ymin": 1461, "ymax": 1554, "confidence": 0.9989050626754761, "label": "defect4"}]}, {"filename": "41.jpg", "rects": [{"xmin": 0, "xmax": 2560, "ymin": 1229, "ymax": 1355, "confidence": 0.9999912977218628, "label": "defect4"}]}, {"filename": "431.jpg", "rects": [{"xmin": 596, "xmax": 702, "ymin": 808, "ymax": 887, "confidence": 0.583876371383667, "label": "defect9"}, {"xmin": 840, "xmax": 915, "ymin": 1628, "ymax": 1694, "confidence": 0.5423728227615356, "label": "defect9"}, {"xmin": 832, "xmax": 915, "ymin": 1209, "ymax": 1286, "confidence": 0.49085766077041626, "label": "defect9"}, {"xmin": 142, "xmax": 267, "ymin": 1385, "ymax": 1486, "confidence": 0.46064454317092896, "label": "defect9"}]}, {"filename": "91.jpg", "rects": [{"xmin": 355, "xmax": 2560, "ymin": 981, "ymax": 1084, "confidence": 0.9982654452323914, "label": "defect0"}, {"xmin": 588, "xmax": 1958, "ymin": 528, "ymax": 682, "confidence": 0.5502796769142151, "label": "defect9"}]}, {"filename": "268.jpg", "rects": [{"xmin": 0, "xmax": 2538, "ymin": 700, "ymax": 807, "confidence": 0.9968312382698059, "label": "defect2"}]}, {"filename": "50.jpg", "rects": [{"xmin": 0, "xmax": 2548, "ymin": 441, "ymax": 528, "confidence": 0.9973815083503723, "label": "defect3"}]}, {"filename": "312.jpg", "rects": [{"xmin": 7, "xmax": 2560, "ymin": 991, "ymax": 1332, "confidence": 0.9994423985481262, "label": "defect8"}]}, {"filename": "62.jpg", "rects": [{"xmin": 0, "xmax": 2542, "ymin": 913, "ymax": 1310, "confidence": 0.9999158382415771, "label": "defect0"}]}, {"filename": "46.jpg", "rects": [{"xmin": 1536, "xmax": 1596, "ymin": 988, "ymax": 1047, "confidence": 1.0, "label": "defect9"}, {"xmin": 439, "xmax": 487, "ymin": 1343, "ymax": 1385, "confidence": 0.9483896493911743, "label": "defect9"}, {"xmin": 2024, "xmax": 2073, "ymin": 1201, "ymax": 1246, "confidence": 0.7270991802215576, "label": "defect9"}]}, {"filename": "492.jpg", "rects": [{"xmin": 227, "xmax": 347, "ymin": 885, "ymax": 989, "confidence": 0.9999779462814331, "label": "defect0"}, {"xmin": 231, "xmax": 339, "ymin": 884, "ymax": 986, "confidence": 0.8057377934455872, "label": "defect9"}]}, {"filename": "171.jpg", "rects": []}, {"filename": "425.jpg", "rects": []}, {"filename": "15.jpg", "rects": [{"xmin": 45, "xmax": 2560, "ymin": 1108, "ymax": 1150, "confidence": 0.9999498128890991, "label": "defect7"}, {"xmin": 1653, "xmax": 1709, "ymin": 961, "ymax": 1012, "confidence": 0.3211970031261444, "label": "defect9"}]}, {"filename": "389.jpg", "rects": [{"xmin": 0, "xmax": 2510, "ymin": 1465, "ymax": 1571, "confidence": 0.9991438388824463, "label": "defect4"}]}, {"filename": "94.jpg", "rects": []}, {"filename": "190.jpg", "rects": [{"xmin": 0, "xmax": 2542, "ymin": 859, "ymax": 1434, "confidence": 0.9992493987083435, "label": "defect8"}]}, {"filename": "285.jpg", "rects": [{"xmin": 856, "xmax": 1125, "ymin": 838, "ymax": 994, "confidence": 0.8702565431594849, "label": "defect9"}, {"xmin": 760, "xmax": 828, "ymin": 1070, "ymax": 1114, "confidence": 0.3880904018878937, "label": "defect9"}, {"xmin": 1952, "xmax": 2002, "ymin": 914, "ymax": 961, "confidence": 0.3222449719905853, "label": "defect9"}, {"xmin": 2364, "xmax": 2539, "ymin": 784, "ymax": 930, "confidence": 0.31453442573547363, "label": "defect9"}, {"xmin": 68, "xmax": 2516, "ymin": 1449, "ymax": 1714, "confidence": 0.7909759283065796, "label": "defect4"}]}, {"filename": "56.jpg", "rects": [{"xmin": 609, "xmax": 680, "ymin": 830, "ymax": 882, "confidence": 0.9944145679473877, "label": "defect9"}, {"xmin": 288, "xmax": 346, "ymin": 725, "ymax": 899, "confidence": 0.643734335899353, "label": "defect9"}, {"xmin": 875, "xmax": 930, "ymin": 825, "ymax": 874, "confidence": 0.34223702549934387, "label": "defect9"}, {"xmin": 20, "xmax": 2499, "ymin": 241, "ymax": 310, "confidence": 0.9366356134414673, "label": "defect3"}]}, {"filename": "309.jpg", "rects": []}, {"filename": "260.jpg", "rects": []}, {"filename": "336.jpg", "rects": [{"xmin": 6, "xmax": 2540, "ymin": 698, "ymax": 810, "confidence": 0.9905098080635071, "label": "defect2"}, {"xmin": 2415, "xmax": 2560, "ymin": 895, "ymax": 1076, "confidence": 0.8058063983917236, "label": "defect9"}, {"xmin": 52, "xmax": 321, "ymin": 938, "ymax": 1083, "confidence": 0.4145430624485016, "label": "defect9"}, {"xmin": 1894, "xmax": 2007, "ymin": 806, "ymax": 866, "confidence": 0.319139689207077, "label": "defect9"}]}, {"filename": "288.jpg", "rects": []}, {"filename": "220.jpg", "rects": [{"xmin": 9, "xmax": 2557, "ymin": 447, "ymax": 547, "confidence": 0.9999136924743652, "label": "defect7"}]}, {"filename": "283.jpg", "rects": [{"xmin": 24, "xmax": 2560, "ymin": 676, "ymax": 1197, "confidence": 0.997048556804657, "label": "defect0"}]}, {"filename": "180.jpg", "rects": [{"xmin": 424, "xmax": 493, "ymin": 620, "ymax": 686, "confidence": 0.9957589507102966, "label": "defect9"}, {"xmin": 2313, "xmax": 2375, "ymin": 598, "ymax": 643, "confidence": 0.9797253012657166, "label": "defect9"}, {"xmin": 1796, "xmax": 1849, "ymin": 563, "ymax": 600, "confidence": 0.860906720161438, "label": "defect6"}]}, {"filename": "450.jpg", "rects": []}, {"filename": "335.jpg", "rects": [{"xmin": 0, "xmax": 2560, "ymin": 1364, "ymax": 1503, "confidence": 0.9999938011169434, "label": "defect2"}]}, {"filename": "289.jpg", "rects": [{"xmin": 9, "xmax": 2552, "ymin": 1039, "ymax": 1581, "confidence": 0.9989726543426514, "label": "defect8"}]}, {"filename": "419.jpg", "rects": [{"xmin": 22, "xmax": 2560, "ymin": 770, "ymax": 1063, "confidence": 0.9989888072013855, "label": "defect0"}]}, {"filename": "60.jpg", "rects": [{"xmin": 321, "xmax": 1231, "ymin": 1299, "ymax": 1569, "confidence": 0.8368055820465088, "label": "defect5"}]}, {"filename": "387.jpg", "rects": [{"xmin": 544, "xmax": 666, "ymin": 1061, "ymax": 1189, "confidence": 0.9999998807907104, "label": "defect9"}, {"xmin": 169, "xmax": 2560, "ymin": 1003, "ymax": 1048, "confidence": 0.9996521472930908, "label": "defect7"}]}, {"filename": "99.jpg", "rects": [{"xmin": 0, "xmax": 2547, "ymin": 966, "ymax": 1013, "confidence": 0.9901766180992126, "label": "defect7"}]}, {"filename": "405.jpg", "rects": []}, {"filename": "86.jpg", "rects": [{"xmin": 1578, "xmax": 1822, "ymin": 919, "ymax": 1128, "confidence": 0.9881365299224854, "label": "defect0"}, {"xmin": 780, "xmax": 850, "ymin": 318, "ymax": 453, "confidence": 0.546620786190033, "label": "defect1"}, {"xmin": 653, "xmax": 714, "ymin": 1457, "ymax": 1511, "confidence": 0.41855016350746155, "label": "defect9"}, {"xmin": 399, "xmax": 560, "ymin": 592, "ymax": 703, "confidence": 0.39481306076049805, "label": "defect9"}, {"xmin": 725, "xmax": 798, "ymin": 1770, "ymax": 1853, "confidence": 0.31961312890052795, "label": "defect9"}]}]}